{"status":"success","match":{"competitionId":87,"seasonId":2015,"matchId":810796,"first_half_start":1442660403,"first_half_stop":1442663113,"second_half_start":1442664122,"second_half_stop":1442666966,"date":1442660400,"teams":{"Home":{"id":165,"name":"TSV 1860 M\u00fcnchen"},"Away":{"id":163,"name":"1. FC Kaiserslautern"}},"statIndexes":{"hit_woodwork":0,"att_pen_goal":1,"att_pen_target":2,"att_pen_off_target":3,"direct_goals":4,"att_ibox_goal":5,"att_ibox_target":6,"att_ibox_off_target":7,"att_ibox_blocked":8,"att_obox_goal":9,"att_obox_target":10,"att_obox_off_target":11,"att_obox_blocked":12,"att_hd_goal":13,"att_hd_target":14,"att_hd_off_target":15,"ShotsClearedoffLineInsideBox_F24":16,"ShotsClearedoffLineOutsideBox_F24":17,"own_goals":18,"goal_assist":19,"key_passes":20,"accurate_back_zone_pass":21,"failed_back_zone_pass":22,"total_fwd_zone_pass":23,"failed_fwd_zone_pass":24,"successful_final_third_passes":25,"long_pass_own_to_opp_success":26,"long_pass_own_to_opp":27,"accurate_cross":28,"failed_cross":29,"won_corners":30,"lost_corners":31,"accurate_corners_intobox":32,"failed_corners_intobox":33,"OutofPlayConceded_F24":34,"won_contest":35,"lost_contest":36,"won_tackle":37,"lost_tackle":38,"last_man_tackle":39,"head_clearance":40,"nohead_clearance":41,"clearance_off_line":42,"interception":43,"aerial_won":44,"aerial_lost":45,"challenge_lost":46,"fouls":47,"was_fouled":48,"penalty_won":49,"hand_ball":50,"penalty_conceded":51,"total_offside":52,"yellow_card":53,"red_card":54,"goals_conceded_ibox":55,"goals_conceded_obox":56,"saved_ibox":57,"saved_obox":58,"penalty_save":59,"good_high_claim":60,"punches":61,"drops":62,"accurate_keeper_throws":63,"failed_keeper_throws":64,"six_yard_block":65,"total_attacking_pass":66,"error_lead_to_goal":67,"error_lead_to_shot":68,"second_yellow":69,"clean_sheet":70,"clean_sheet_part":71,"goal_assist_openplay":72,"clean_sheet_away":73,"gk_smother":74,"key_passes_open_play":75,"ball_recovery":76,"shield_ball_oop":77,"accurate_through_ball":78,"SavesDiving_F24":79,"SavesStanding_F24":80,"SavesStooping_F24":81,"SavesReaching_F24":82,"SavesFingertip_F24":83,"SavesCaught_F24":84,"SavesCollected_F24":85,"SavesParriedSafe_F24":86,"SavesParriedDanger_F24":87,"SavesHands_F24":88,"SavesFeet_F24":89,"SavesBody_F24":90,"Matchwinner_Goal":91,"Equalizer_Goal":92,"att_pen_miss":93,"att_pen_post":94,"goals":95,"goals_openplay":96,"att_ibox_miss":97,"att_ibox_post":98,"att_obox_miss":99,"att_obox_post":100,"att_hd_miss":101,"att_hd_post":102,"att_ibox_own_goal":103,"att_obox_own_goal":104,"total_att_assist":105,"total_back_zone_pass":106,"accurate_fwd_zone_pass":107,"total_cross":108,"total_corners_intobox":109,"total_contest":110,"total_tackle":111,"total_clearance":112,"total_high_claim":113,"keeper_throws":114,"att_assist_openplay":115},"players":{"85367":{"side":"Home","team":165,"firstname":"Vitus","lastname":"Eicher","knownname":"","position":"Goalkeeper","number":"1","defaultPosition":"Goalkeeper"},"85368":{"side":"Home","team":165,"firstname":"Christopher","lastname":"Schindler","knownname":"","position":"Defender","number":"26","defaultPosition":"Defender"},"192848":{"side":"Home","team":165,"firstname":"Maximilian","lastname":"Wittek","knownname":"","position":"Defender","number":"3","defaultPosition":"Defender"},"27332":{"side":"Home","team":165,"firstname":"Kai","lastname":"B\u00fclow","knownname":"","position":"Defender","number":"4","defaultPosition":"Defender"},"61798":{"side":"Home","team":165,"firstname":"Gary","lastname":"Kagelmacher","knownname":"","position":"Defender","number":"25","defaultPosition":"Defender"},"149037":{"side":"Home","team":165,"firstname":"Milos","lastname":"Degenek","knownname":"","position":"Midfielder","number":"30","defaultPosition":"Defender"},"192849":{"side":"Home","team":165,"firstname":"Marius","lastname":"Wolf","knownname":"","position":"Midfielder","number":"27","defaultPosition":"Forward"},"20724":{"side":"Home","team":165,"firstname":"Daniel","lastname":"Adlung","knownname":"","position":"Midfielder","number":"11","defaultPosition":"Midfielder"},"77930":{"side":"Home","team":165,"firstname":"Daylon","lastname":"Claasen","knownname":"","position":"Midfielder","number":"7","defaultPosition":"Midfielder"},"101072":{"side":"Home","team":165,"firstname":"Korbinian","lastname":"Vollmann","knownname":"","position":"Forward","number":"33","defaultPosition":"Midfielder"},"84886":{"side":"Home","team":165,"firstname":"Stefan","lastname":"Mugosa","knownname":"","position":"Forward","number":"9","defaultPosition":"Forward"},"85077":{"side":"Home","team":165,"firstname":"Vladimir","lastname":"Kovac","knownname":"","position":"Midfielder","number":"39","defaultPosition":"Defender"},"88248":{"side":"Home","team":165,"firstname":"Stefan","lastname":"Ortega Moreno","knownname":"","position":"Goalkeeper","number":"24","defaultPosition":"Goalkeeper"},"200681":{"side":"Home","team":165,"firstname":"Fejsal","lastname":"Mulic","knownname":"","position":"Forward","number":"34","defaultPosition":"Forward"},"215031":{"side":"Home","team":165,"firstname":"Stephane","lastname":"Mvibudulu","knownname":"","position":"Forward","number":"36","defaultPosition":"Forward"},"51978":{"side":"Home","team":165,"firstname":"Rodnei Francisco","lastname":"De Lima","knownname":"Rodnei","position":"Defender","number":"8","defaultPosition":"Defender"},"62478":{"side":"Home","team":165,"firstname":"Michael","lastname":"Liendl","knownname":"","position":"Midfielder","number":"10","defaultPosition":"Midfielder"},"68654":{"side":"Home","team":165,"firstname":"Krisztian","lastname":"Simon","knownname":"Krisztian Simon","position":"Forward","number":"14","defaultPosition":"Forward"},"112974":{"side":"Away","team":163,"firstname":"Marius","lastname":"M\u00fcller","knownname":"","position":"Goalkeeper","number":"1","defaultPosition":"Goalkeeper"},"166721":{"side":"Away","team":163,"firstname":"Jean","lastname":"Zimmer","knownname":"","position":"Defender","number":"39","defaultPosition":"Defender"},"53829":{"side":"Away","team":163,"firstname":"Patrick","lastname":"Ziegler","knownname":"","position":"Defender","number":"4","defaultPosition":"Defender"},"54284":{"side":"Away","team":163,"firstname":"Chris","lastname":"L\u00f6we","knownname":"","position":"Defender","number":"31","defaultPosition":"Defender"},"58618":{"side":"Away","team":163,"firstname":"Tim","lastname":"Heubach","knownname":"","position":"Defender","number":"3","defaultPosition":"Defender"},"71737":{"side":"Away","team":163,"firstname":"Marcus","lastname":"Piossek","knownname":"","position":"Midfielder","number":"8","defaultPosition":"Midfielder"},"88909":{"side":"Away","team":163,"firstname":"Alexander","lastname":"Ring","knownname":"","position":"Midfielder","number":"6","defaultPosition":"Midfielder"},"28156":{"side":"Away","team":163,"firstname":"Daniel","lastname":"Halfar","knownname":"","position":"Midfielder","number":"28","defaultPosition":"Midfielder"},"61876":{"side":"Away","team":163,"firstname":"Ruben","lastname":"Jenssen","knownname":"","position":"Midfielder","number":"11","defaultPosition":"Midfielder"},"67048":{"side":"Away","team":163,"firstname":"Robert","lastname":"Pich","knownname":"","position":"Midfielder","number":"13","defaultPosition":"Midfielder"},"107091":{"side":"Away","team":163,"firstname":"Kacper","lastname":"Przybylko","knownname":"","position":"Forward","number":"20","defaultPosition":"Forward"},"108906":{"side":"Away","team":163,"firstname":"Maurice","lastname":"Deville","knownname":"","position":"Forward","number":"27","defaultPosition":"Forward"},"118338":{"side":"Away","team":163,"firstname":"Andr\u00e9","lastname":"Fomitschow","knownname":"","position":"Midfielder","number":"17","defaultPosition":"Defender"},"170801":{"side":"Away","team":163,"firstname":"Sascha","lastname":"Mockenhaupt","knownname":"","position":"Defender","number":"5","defaultPosition":"Defender"},"20374":{"side":"Away","team":163,"firstname":"Markus","lastname":"Karl","knownname":"","position":"Midfielder","number":"37","defaultPosition":"Midfielder"},"179028":{"side":"Away","team":163,"firstname":"Erik","lastname":"Thommy","knownname":"","position":"Midfielder","number":"18","defaultPosition":"Midfielder"},"209402":{"side":"Away","team":163,"firstname":"Lukas","lastname":"G\u00f6rtler","knownname":"","position":"Forward","number":"9","defaultPosition":"Forward"},"71730":{"side":"Away","team":163,"firstname":"Zlatan","lastname":"Alomerovic","knownname":"","position":"Goalkeeper","number":"33","defaultPosition":"Goalkeeper"}},"snapshots":[{"timestamp":1442667009,"period":"FullTime","type":"Result","matchTime":93,"players":{"85367":{"stats":[0,0,0,0,0,0,0,0,0,0,0,0,0,0,0,0,0,0,0,0,0,7,0,22,15,0,7,22,0,0,0,0,0,0,1,0,0,0,0,0,0,1,0,0,0,1,0,0,0,0,0,0,0,0,0,0,1,3,0,0,2,0,0,2,0,0,0,0,0,0,0,0,0,0,0,0,8,0,0,1,1,1,0,0,0,1,0,2,2,1,0,0,0],"participation":1,"participationMin":93,"index":{"total":289,"off":79.25,"def":209.75}},"85368":{"stats":[0,0,0,0,0,0,0,0,1,0,0,0,0,0,0,0,0,0,0,0,0,23,2,17,10,1,5,12,0,0,0,1,0,0,3,0,0,1,0,0,3,7,0,5,8,1,1,1,0,0,0,0,0,0,0,0,1,0,0,0,0,0,0,0,0,0,0,0,0,0,0,0,0,0,0,0,3,0,0,0,0,0,0,0,0,0,0,0,0,0,0,0,0],"participation":1,"participationMin":93,"index":{"total":829.75,"off":33.25,"def":796.5}},"192848":{"stats":[0,0,0,0,0,0,0,0,0,0,0,0,0,0,0,0,0,0,0,0,0,9,6,23,11,8,4,6,0,4,1,1,0,0,6,3,0,1,0,0,2,5,0,0,2,2,1,1,2,0,0,0,0,0,0,0,1,0,0,0,0,0,0,0,0,0,0,1,0,0,0,0,0,0,0,0,4,2,0,0,0,0,0,0,0,0,0,0,0,0,0,0,0],"participation":1,"participationMin":93,"index":{"total":-37.75,"off":-45.75,"def":8}},"27332":{"stats":[0,0,0,0,0,0,0,1,0,0,0,0,0,0,0,1,0,0,0,0,0,20,3,12,6,3,3,8,0,0,0,0,0,0,5,0,0,1,0,0,4,3,0,5,9,4,1,1,2,0,0,0,0,0,0,0,1,0,0,0,0,0,0,0,0,0,0,0,0,0,0,0,0,0,0,0,3,0,0,0,0,0,0,0,0,0,0,0,0,0,0,0,0],"participation":1,"participationMin":93,"index":{"total":731.75,"off":83.125,"def":648.625}},"61798":{"stats":[0,0,0,0,0,0,0,0,0,0,0,2,0,0,0,0,0,0,0,0,0,6,4,19,12,3,2,9,0,2,0,1,0,0,6,0,0,5,1,0,0,1,0,3,5,1,3,5,1,0,0,0,0,0,0,0,1,0,0,0,0,0,0,0,0,0,0,0,0,0,0,0,0,0,0,0,2,1,0,0,0,0,0,0,0,0,0,0,0,0,0,0,0],"participation":1,"participationMin":93,"index":{"total":72.3,"off":-142.575,"def":214.875}},"149037":{"stats":[0,0,0,0,0,0,0,1,0,1,0,0,0,0,0,1,0,0,0,0,1,18,1,14,9,2,1,6,0,1,0,1,0,0,3,0,0,1,0,0,0,3,0,3,3,1,1,0,1,0,0,0,0,1,0,0,1,0,0,0,0,0,0,0,0,0,0,0,0,0,0,0,0,0,0,1,2,0,0,0,0,0,0,0,0,0,0,0,0,0,0,0,0],"participation":1,"participationMin":93,"index":{"total":519,"off":325,"def":194}},"192849":{"stats":[0,0,0,0,0,0,0,0,0,0,0,0,1,0,0,0,0,0,0,0,1,4,2,17,6,7,0,1,0,1,1,0,0,0,5,1,1,0,0,0,0,1,0,3,0,0,0,0,4,0,0,0,0,0,0,0,1,0,0,0,0,0,0,0,0,0,0,0,0,0,0,0,0,0,0,1,1,0,0,0,0,0,0,0,0,0,0,0,0,0,0,0,0],"participation":1,"participationMin":93,"index":{"total":253.45,"off":108.95,"def":144.5}},"20724":{"stats":[0,0,0,0,0,0,0,0,0,0,1,0,0,0,0,0,0,0,0,0,4,14,4,45,15,21,5,10,2,1,0,1,1,0,1,1,0,1,0,0,0,0,0,2,1,1,1,3,0,0,2,0,0,1,0,0,1,0,0,0,0,0,0,0,0,0,0,0,0,0,0,0,0,0,0,2,5,0,0,0,0,0,0,0,0,0,0,0,0,0,0,0,0],"participation":1,"participationMin":93,"index":{"total":170.65,"off":262.4,"def":-91.75}},"77930":{"stats":[0,0,0,0,0,0,0,0,0,0,0,0,0,0,0,0,0,0,0,0,0,6,2,16,4,6,2,3,1,0,0,0,0,0,1,2,2,3,1,0,0,0,0,2,1,3,1,2,1,0,0,0,0,1,0,0,1,0,0,0,0,0,0,0,0,0,0,0,0,0,0,0,0,0,0,0,8,0,0,0,0,0,0,0,0,0,0,0,0,0,0,0,0],"participation":0.86021505376344,"participationMin":80,"index":{"total":50.25,"off":20.5,"def":29.75}},"101072":{"stats":[1,0,0,0,0,0,0,1,0,0,1,0,1,0,0,0,0,0,0,0,0,9,1,20,10,3,1,3,1,4,3,0,1,3,0,4,0,2,0,0,0,0,0,0,1,3,2,0,1,0,0,0,0,0,0,0,1,0,0,0,0,0,0,0,0,0,0,0,0,0,0,0,0,0,0,0,2,0,0,0,0,0,0,0,0,0,0,0,0,0,0,0,0],"participation":0.91397849462366,"participationMin":85,"index":{"total":546.9,"off":538.9,"def":8}},"84886":{"stats":[0,0,0,0,0,0,0,0,0,0,0,0,0,0,0,0,0,0,0,0,0,2,2,12,4,1,2,3,0,1,0,0,0,0,1,0,0,0,0,0,0,0,0,0,6,13,0,2,4,0,0,0,1,0,0,0,1,0,0,0,0,0,0,0,0,0,0,0,0,0,0,0,0,0,0,0,2,0,0,0,0,0,0,0,0,0,0,0,0,0,0,0,0],"participation":0.80645161290323,"participationMin":75,"index":{"total":-16,"off":-9.5,"def":-6.5}},"85077":{"stats":[0,0,0,0,0,0,0,0,0,0,0,0,0,0,0,0,0,0,0,0,0,0,0,0,0,0,0,0,0,0,0,0,0,0,0,0,0,0,0,0,0,0,0,0,0,0,0,0,0,0,0,0,0,0,0,0,0,0,0,0,0,0,0,0,0,0,0,0,0,0,0,0,0,0,0,0,0,0,0,0,0,0,0,0,0,0,0,0,0,0,0,0,0],"participation":0,"participationMin":0,"index":{"total":0,"off":0,"def":0}},"88248":{"stats":[0,0,0,0,0,0,0,0,0,0,0,0,0,0,0,0,0,0,0,0,0,0,0,0,0,0,0,0,0,0,0,0,0,0,0,0,0,0,0,0,0,0,0,0,0,0,0,0,0,0,0,0,0,0,0,0,0,0,0,0,0,0,0,0,0,0,0,0,0,0,0,0,0,0,0,0,0,0,0,0,0,0,0,0,0,0,0,0,0,0,0,0,0],"participation":0,"participationMin":0,"index":{"total":0,"off":0,"def":0}},"200681":{"stats":[0,0,0,0,0,0,0,0,0,0,0,0,0,0,0,0,0,0,0,0,0,1,0,2,2,0,0,0,0,0,0,0,0,0,0,0,0,0,0,0,1,0,0,0,4,1,0,0,0,0,0,0,1,0,0,0,0,0,0,0,0,0,0,0,0,0,0,0,0,0,0,0,0,0,0,0,0,0,0,0,0,0,0,0,0,0,0,0,0,0,0,0,0],"participation":0.19354838709677,"participationMin":18,"index":{"total":24,"off":-11.5,"def":35.5}},"215031":{"stats":[0,0,0,0,0,0,0,0,0,0,0,0,0,0,0,0,0,0,0,0,0,2,1,2,1,0,0,0,0,0,0,0,0,0,0,1,0,0,0,0,0,0,0,0,0,3,0,1,0,0,0,0,0,0,0,0,0,0,0,0,0,0,0,0,0,0,0,0,0,0,0,0,0,0,0,0,3,0,0,0,0,0,0,0,0,0,0,0,0,0,0,0,0],"participation":0.13978494623656,"participationMin":13,"index":{"total":-29,"off":-3,"def":-26}},"51978":{"stats":[0,0,0,0,0,0,0,0,0,0,0,0,0,0,0,0,0,0,0,0,0,0,0,0,0,0,0,0,0,0,0,0,0,0,0,0,0,0,0,0,0,0,0,0,0,0,0,0,0,0,0,0,0,0,0,0,0,0,0,0,0,0,0,0,0,0,0,0,0,0,0,0,0,0,0,0,0,0,0,0,0,0,0,0,0,0,0,0,0,0,0,0,0],"participation":0,"participationMin":0,"index":{"total":0,"off":0,"def":0}},"62478":{"stats":[0,0,0,0,0,0,0,0,0,0,0,0,0,0,0,0,0,0,0,0,0,0,0,1,1,0,0,0,0,0,0,0,0,0,0,0,0,0,0,0,0,0,0,0,1,0,0,0,0,0,0,0,0,0,0,0,0,0,0,0,0,0,0,0,0,0,0,0,0,0,0,0,0,0,0,0,0,0,0,0,0,0,0,0,0,0,0,0,0,0,0,0,0],"participation":0.086021505376344,"participationMin":8,"index":{"total":4.25,"off":-4.375,"def":8.625}},"68654":{"stats":[0,0,0,0,0,0,0,0,0,0,0,0,0,0,0,0,0,0,0,0,0,0,0,0,0,0,0,0,0,0,0,0,0,0,0,0,0,0,0,0,0,0,0,0,0,0,0,0,0,0,0,0,0,0,0,0,0,0,0,0,0,0,0,0,0,0,0,0,0,0,0,0,0,0,0,0,0,0,0,0,0,0,0,0,0,0,0,0,0,0,0,0,0],"participation":0,"participationMin":0,"index":{"total":0,"off":0,"def":0}},"112974":{"stats":[0,0,0,0,0,0,0,0,0,0,0,0,0,0,0,0,0,0,0,0,0,9,0,19,14,4,5,19,0,0,0,1,0,0,1,1,0,0,0,0,0,1,0,0,0,0,0,0,0,0,0,0,0,0,0,0,1,0,2,0,1,1,0,4,0,0,0,0,0,0,0,0,0,0,0,0,12,0,0,1,1,0,0,0,0,0,2,0,2,0,0,0,0],"participation":1,"participationMin":93,"index":{"total":346,"off":106,"def":240}},"166721":{"stats":[0,0,0,0,0,0,0,1,0,0,0,0,1,0,0,0,0,0,0,0,1,5,8,19,7,9,0,4,0,0,1,1,0,0,3,0,1,1,0,0,1,2,0,1,0,0,1,3,1,0,0,0,0,1,0,0,1,0,0,0,0,0,0,0,0,0,0,0,0,0,0,0,0,0,0,1,6,0,0,0,0,0,0,0,0,0,0,0,0,0,0,0,0],"participation":1,"participationMin":93,"index":{"total":-108.35,"off":-110.1,"def":1.75}},"53829":{"stats":[0,0,0,0,0,0,0,0,0,0,0,0,0,0,0,0,0,0,0,0,0,22,4,16,5,6,3,5,0,1,0,0,0,0,3,1,0,0,0,0,3,2,0,4,6,2,2,0,0,0,0,0,0,0,0,0,1,0,0,0,0,0,0,0,0,0,0,0,0,0,0,0,0,0,0,0,2,0,0,0,0,0,0,0,0,0,0,0,0,0,0,0,0],"participation":1,"participationMin":93,"index":{"total":441.5,"off":60.25,"def":381.25}},"54284":{"stats":[0,0,0,0,0,0,0,1,0,0,0,1,0,0,0,0,0,0,0,0,1,27,1,39,14,18,6,9,0,5,0,1,0,2,9,0,1,1,0,0,3,1,0,1,2,0,0,0,1,0,0,0,0,0,0,0,1,0,0,0,0,0,0,0,0,0,0,0,0,0,0,0,0,0,0,1,7,0,0,0,0,0,0,0,0,0,0,0,0,0,0,0,0],"participation":1,"participationMin":93,"index":{"total":418.25,"off":93.25,"def":325}},"58618":{"stats":[0,0,0,0,0,0,0,1,0,0,0,0,0,0,0,1,0,0,0,0,0,24,3,31,15,5,11,25,0,0,1,1,0,0,2,0,0,0,0,0,0,0,0,4,6,1,0,0,0,0,0,0,0,0,0,0,1,0,0,0,0,0,0,0,0,0,0,0,0,0,0,0,0,0,0,0,2,0,0,0,0,0,0,0,0,0,0,0,0,0,0,0,0],"participation":1,"participationMin":93,"index":{"total":303.25,"off":62.25,"def":241}},"71737":{"stats":[0,0,0,0,0,0,0,0,0,0,0,1,0,0,0,0,0,0,0,0,0,3,3,10,3,4,0,1,0,0,0,0,0,0,3,1,0,4,0,0,0,1,0,3,1,4,3,2,2,0,0,0,0,0,0,0,1,0,0,0,0,0,0,0,0,0,0,1,0,0,0,0,0,0,0,0,4,0,0,0,0,0,0,0,0,0,0,0,0,0,0,0,0],"participation":0.59139784946237,"participationMin":55,"index":{"total":-161.65,"off":2.225,"def":-163.875}},"88909":{"stats":[0,0,0,0,0,0,0,0,0,0,0,0,0,0,0,0,0,0,0,0,1,29,2,27,7,7,8,10,0,0,0,0,0,0,3,1,0,5,0,0,0,0,0,1,4,10,1,5,0,0,0,0,0,0,0,0,1,0,0,0,0,0,0,0,0,0,0,0,0,0,0,0,0,0,0,1,5,0,0,0,0,0,0,0,0,0,0,0,0,0,0,0,0],"participation":1,"participationMin":93,"index":{"total":104.45,"off":26.7,"def":77.75}},"28156":{"stats":[1,0,0,0,0,0,0,0,0,0,0,1,0,0,0,0,0,0,0,0,1,5,2,45,19,19,1,3,0,6,0,0,0,2,3,0,2,2,0,0,0,0,0,1,1,1,1,2,3,0,0,0,0,0,0,0,1,0,0,0,0,0,0,0,0,0,0,0,0,0,0,0,0,0,0,0,2,0,0,0,0,0,0,0,0,0,0,0,0,0,0,0,0],"participation":1,"participationMin":93,"index":{"total":79.3,"off":27.05,"def":52.25}},"61876":{"stats":[0,0,0,0,0,0,1,0,0,1,0,0,0,0,0,0,0,0,0,0,1,13,3,37,12,14,6,9,0,2,1,0,0,0,1,2,0,1,0,0,1,1,0,1,4,3,4,1,3,0,0,0,0,1,0,0,1,0,0,0,0,0,0,0,0,0,0,0,0,0,0,0,0,0,0,1,7,0,0,0,0,0,0,0,0,0,0,0,0,0,0,0,1],"participation":1,"participationMin":93,"index":{"total":679.2,"off":572.325,"def":106.875}},"67048":{"stats":[0,0,0,0,0,0,0,0,0,0,0,1,1,0,0,1,0,0,0,0,3,8,2,29,14,12,0,1,0,1,1,0,0,0,1,1,3,1,0,0,1,0,0,0,2,7,0,0,2,0,0,0,0,0,0,0,1,0,0,0,0,0,0,0,0,0,0,0,0,0,0,0,0,0,0,3,2,0,0,0,0,0,0,0,0,0,0,0,0,0,0,0,0],"participation":0.86021505376344,"participationMin":80,"index":{"total":121.15,"off":67.525,"def":53.625}},"107091":{"stats":[0,0,0,0,0,0,1,1,0,0,0,1,0,0,1,0,0,0,0,0,1,3,1,18,5,8,3,3,0,1,1,1,0,0,1,1,4,1,0,0,1,0,0,0,6,7,0,2,2,0,0,0,0,0,0,0,1,0,0,0,0,0,0,0,0,0,0,0,0,0,0,0,0,0,0,1,1,0,0,0,0,0,0,0,0,0,0,0,0,0,0,0,0],"participation":1,"participationMin":93,"index":{"total":315.8,"off":298.3,"def":17.5}},"108906":{"stats":[0,0,0,0,0,0,0,0,0,0,0,0,0,0,0,0,0,0,0,0,0,0,0,5,1,3,0,0,0,0,0,0,0,0,1,0,0,0,0,0,0,0,0,0,1,1,0,0,0,0,0,0,0,0,0,0,0,0,0,0,0,0,0,0,0,0,0,0,0,0,0,0,0,0,0,0,1,0,0,0,0,0,0,0,0,0,0,0,0,0,0,0,0],"participation":0.13978494623656,"participationMin":13,"index":{"total":20,"off":19.5,"def":0.5}},"118338":{"stats":[0,0,0,0,0,0,0,0,0,0,0,0,0,0,0,0,0,0,0,0,0,0,0,0,0,0,0,0,0,0,0,0,0,0,0,0,0,0,0,0,0,0,0,0,0,0,0,0,0,0,0,0,0,0,0,0,0,0,0,0,0,0,0,0,0,0,0,0,0,0,0,0,0,0,0,0,0,0,0,0,0,0,0,0,0,0,0,0,0,0,0,0,0],"participation":0,"participationMin":0,"index":{"total":0,"off":0,"def":0}},"170801":{"stats":[0,0,0,0,0,0,0,0,0,0,0,0,0,0,0,0,0,0,0,0,0,0,0,0,0,0,0,0,0,0,0,0,0,0,0,0,0,0,0,0,0,0,0,0,0,0,0,0,0,0,0,0,0,0,0,0,0,0,0,0,0,0,0,0,0,0,0,0,0,0,0,0,0,0,0,0,0,0,0,0,0,0,0,0,0,0,0,0,0,0,0,0,0],"participation":0,"participationMin":0,"index":{"total":0,"off":0,"def":0}},"20374":{"stats":[0,0,0,0,0,0,0,0,0,0,0,0,0,0,0,0,0,0,0,0,0,0,0,0,0,0,0,0,0,0,0,0,0,0,0,0,0,0,0,0,0,0,0,0,0,0,0,0,0,0,0,0,0,0,0,0,0,0,0,0,0,0,0,0,0,0,0,0,0,0,0,0,0,0,0,0,0,0,0,0,0,0,0,0,0,0,0,0,0,0,0,0,0],"participation":0,"participationMin":0,"index":{"total":0,"off":0,"def":0}},"179028":{"stats":[0,0,0,0,0,0,0,0,0,0,0,0,0,0,0,0,0,0,0,0,0,0,0,0,0,0,0,0,0,0,0,0,0,0,0,0,0,0,0,0,0,0,0,0,0,0,0,0,0,0,0,0,0,0,0,0,0,0,0,0,0,0,0,0,0,0,0,0,0,0,0,0,0,0,0,0,0,0,0,0,0,0,0,0,0,0,0,0,0,0,0,0,0],"participation":0,"participationMin":0,"index":{"total":0,"off":0,"def":0}},"209402":{"stats":[0,0,0,0,0,0,1,0,0,0,0,0,0,0,0,0,0,0,0,0,1,2,0,11,4,6,0,1,0,0,0,0,0,0,1,3,1,0,0,0,0,0,0,0,1,5,0,1,0,0,0,0,0,0,0,0,0,0,0,0,0,0,0,0,0,0,0,0,0,0,0,0,0,0,0,1,2,0,0,0,0,0,0,0,0,0,0,0,0,0,0,0,0],"participation":0.40860215053763,"participationMin":38,"index":{"total":202.6,"off":224.6,"def":-22}},"71730":{"stats":[0,0,0,0,0,0,0,0,0,0,0,0,0,0,0,0,0,0,0,0,0,0,0,0,0,0,0,0,0,0,0,0,0,0,0,0,0,0,0,0,0,0,0,0,0,0,0,0,0,0,0,0,0,0,0,0,0,0,0,0,0,0,0,0,0,0,0,0,0,0,0,0,0,0,0,0,0,0,0,0,0,0,0,0,0,0,0,0,0,0,0,0,0],"participation":0,"participationMin":0,"index":{"total":0,"off":0,"def":0}}},"score_Home":1,"score_Away":1,"running":false,"progress":5580,"sinceMatchBegin":6606,"f9Id":31356,"F24Id":31355,"goals":{"0":{"pID":149037,"tID":165,"order":1014037,"own":false},"1":{"pID":61876,"tID":163,"order":2058058,"own":false},"score_home":1,"score_away":1,"last_home":{"pID":149037,"tID":165,"order":1014037,"own":false},"last_away":{"pID":61876,"tID":163,"order":2058058,"own":false}},"relevance":100,"halfscore_Home":1,"halfscore_Away":0}],"range":{"from":null,"till":null}}}