{"status":"success","match":{"competitionId":98,"seasonId":2016,"matchId":842804,"first_half_start":1467508235,"first_half_stop":1467511128,"second_half_start":1467512114,"second_half_stop":1467515174,"date":1467507600,"teams":{"Home":{"id":1897,"name":"Houston Dynamo"},"Away":{"id":5513,"name":"Philadelphia Union"}},"statIndexes":{"hit_woodwork":0,"att_pen_goal":1,"att_pen_target":2,"att_pen_off_target":3,"direct_goals":4,"att_ibox_goal":5,"att_ibox_target":6,"att_ibox_off_target":7,"att_ibox_blocked":8,"att_obox_goal":9,"att_obox_target":10,"att_obox_off_target":11,"att_obox_blocked":12,"att_hd_goal":13,"att_hd_target":14,"att_hd_off_target":15,"ShotsClearedoffLineInsideBox_F24":16,"ShotsClearedoffLineOutsideBox_F24":17,"own_goals":18,"goal_assist":19,"key_passes":20,"accurate_back_zone_pass":21,"failed_back_zone_pass":22,"total_fwd_zone_pass":23,"failed_fwd_zone_pass":24,"successful_final_third_passes":25,"long_pass_own_to_opp_success":26,"long_pass_own_to_opp":27,"accurate_cross":28,"failed_cross":29,"won_corners":30,"lost_corners":31,"accurate_corners_intobox":32,"failed_corners_intobox":33,"OutofPlayConceded_F24":34,"won_contest":35,"lost_contest":36,"won_tackle":37,"lost_tackle":38,"last_man_tackle":39,"head_clearance":40,"nohead_clearance":41,"clearance_off_line":42,"interception":43,"aerial_won":44,"aerial_lost":45,"challenge_lost":46,"fouls":47,"was_fouled":48,"penalty_won":49,"hand_ball":50,"penalty_conceded":51,"total_offside":52,"yellow_card":53,"red_card":54,"goals_conceded_ibox":55,"goals_conceded_obox":56,"saved_ibox":57,"saved_obox":58,"penalty_save":59,"good_high_claim":60,"punches":61,"drops":62,"accurate_keeper_throws":63,"failed_keeper_throws":64,"six_yard_block":65,"total_attacking_pass":66,"error_lead_to_goal":67,"error_lead_to_shot":68,"second_yellow":69,"clean_sheet":70,"clean_sheet_part":71,"goal_assist_openplay":72,"clean_sheet_away":73,"gk_smother":74,"key_passes_open_play":75,"ball_recovery":76,"shield_ball_oop":77,"accurate_through_ball":78,"SavesDiving_F24":79,"SavesStanding_F24":80,"SavesStooping_F24":81,"SavesReaching_F24":82,"SavesFingertip_F24":83,"SavesCaught_F24":84,"SavesCollected_F24":85,"SavesParriedSafe_F24":86,"SavesParriedDanger_F24":87,"SavesHands_F24":88,"SavesFeet_F24":89,"SavesBody_F24":90,"Matchwinner_Goal":91,"Equalizer_Goal":92,"att_pen_miss":93,"att_pen_post":94,"goals":95,"goals_openplay":96,"att_ibox_miss":97,"att_ibox_post":98,"att_obox_miss":99,"att_obox_post":100,"att_hd_miss":101,"att_hd_post":102,"att_ibox_own_goal":103,"att_obox_own_goal":104,"total_att_assist":105,"total_back_zone_pass":106,"accurate_fwd_zone_pass":107,"total_cross":108,"total_corners_intobox":109,"total_contest":110,"total_tackle":111,"total_clearance":112,"total_high_claim":113,"keeper_throws":114,"att_assist_openplay":115},"players":{"83274":{"side":"Home","team":1897,"firstname":"Tyler","lastname":"Deric","knownname":"","position":"Goalkeeper","number":"1","defaultPosition":"Goalkeeper"},"50143":{"side":"Home","team":1897,"firstname":"David","lastname":"Horst","knownname":"","position":"Defender","number":"18","defaultPosition":"Defender"},"12875":{"side":"Home","team":1897,"firstname":"DaMarcus","lastname":"Beasley","knownname":"","position":"Defender","number":"7","defaultPosition":"Defender"},"90116":{"side":"Home","team":1897,"firstname":"Raul","lastname":"Rodriguez","knownname":"Ra\u00fal Rodr\u00edguez","position":"Defender","number":"5","defaultPosition":"Defender"},"95228":{"side":"Home","team":1897,"firstname":"Jalil","lastname":"Anibaba","knownname":"","position":"Defender","number":"2","defaultPosition":"Defender"},"20568":{"side":"Home","team":1897,"firstname":"Giles","lastname":"Barnes","knownname":"","position":"Midfielder","number":"10","defaultPosition":"Midfielder"},"83072":{"side":"Home","team":1897,"firstname":"Collen","lastname":"Warner","knownname":"","position":"Midfielder","number":"26","defaultPosition":"Midfielder"},"55209":{"side":"Home","team":1897,"firstname":"Oscar Boniek","lastname":"Garcia Ramirez","knownname":"Boniek Garc\u00eda","position":"Midfielder","number":"27","defaultPosition":"Midfielder"},"108216":{"side":"Home","team":1897,"firstname":"Alexandre Monteiro","lastname":"De Lima","knownname":"Alex","position":"Midfielder","number":"14","defaultPosition":"Midfielder"},"33823":{"side":"Home","team":1897,"firstname":"Ricardo","lastname":"Clark","knownname":"","position":"Midfielder","number":"13","defaultPosition":"Midfielder"},"95272":{"side":"Home","team":1897,"firstname":"Will","lastname":"Bruin","knownname":"","position":"Forward","number":"12","defaultPosition":"Forward"},"78016":{"side":"Home","team":1897,"firstname":"Sheanon","lastname":"Williams","knownname":"","position":"Defender","number":"22","defaultPosition":"Defender"},"49541":{"side":"Home","team":1897,"firstname":"Cristi\u00e1n","lastname":"Maidana","knownname":"","position":"Midfielder","number":"8","defaultPosition":"Midfielder"},"20086":{"side":"Home","team":1897,"firstname":"Agustin","lastname":"Garc\u00eda Iniguez","knownname":"Agus","position":"Defender","number":"4","defaultPosition":"Defender"},"95309":{"side":"Home","team":1897,"firstname":"Joe","lastname":"Willis","knownname":"","position":"Goalkeeper","number":"31","defaultPosition":"Goalkeeper"},"87946":{"side":"Home","team":1897,"firstname":"David","lastname":"Mateos Rocha","knownname":"David Rocha","position":"Midfielder","number":"6","defaultPosition":"Midfielder"},"177658":{"side":"Home","team":1897,"firstname":"Mauro","lastname":"Manotas","knownname":"","position":"Forward","number":"19","defaultPosition":"Forward"},"110633":{"side":"Home","team":1897,"firstname":"Andrew","lastname":"Wenger","knownname":"","position":"Midfielder","number":"11","defaultPosition":"Midfielder"},"163906":{"side":"Away","team":5513,"firstname":"Andre","lastname":"Blake","knownname":"","position":"Goalkeeper","number":"1","defaultPosition":"Goalkeeper"},"132000":{"side":"Away","team":5513,"firstname":"Fabio Alves","lastname":"Macedo","knownname":"Fabinho","position":"Defender","number":"33","defaultPosition":"Defender"},"202192":{"side":"Away","team":5513,"firstname":"Joshua","lastname":"Yaro","knownname":"","position":"Defender","number":"15","defaultPosition":"Defender"},"127541":{"side":"Away","team":5513,"firstname":"Keegan","lastname":"Rosenberry","knownname":"","position":"Defender","number":"12","defaultPosition":"Defender"},"178000":{"side":"Away","team":5513,"firstname":"Richard","lastname":"Marquez","knownname":"Richie Marquez","position":"Defender","number":"16","defaultPosition":"Defender"},"86574":{"side":"Away","team":5513,"firstname":"Roland","lastname":"Alberg","knownname":"","position":"Midfielder","number":"6","defaultPosition":"Midfielder"},"28091":{"side":"Away","team":5513,"firstname":"Brian","lastname":"Carroll","knownname":"","position":"Midfielder","number":"7","defaultPosition":"Midfielder"},"18094":{"side":"Away","team":5513,"firstname":"Tranquillo","lastname":"Barnetta","knownname":"","position":"Midfielder","number":"10","defaultPosition":"Midfielder"},"110575":{"side":"Away","team":5513,"firstname":"Warren","lastname":"Creavalle","knownname":"","position":"Midfielder","number":"2","defaultPosition":"Midfielder"},"45120":{"side":"Away","team":5513,"firstname":"Ilson","lastname":"Pereira Dias J\u00fanior","knownname":"Ilsinho","position":"Midfielder","number":"25","defaultPosition":"Midfielder"},"60152":{"side":"Away","team":5513,"firstname":"Chris","lastname":"Pontius","knownname":"","position":"Forward","number":"13","defaultPosition":"Midfielder"},"110974":{"side":"Away","team":5513,"firstname":"Raymon","lastname":"Gaddis","knownname":"","position":"Defender","number":"28","defaultPosition":"Defender"},"163565":{"side":"Away","team":5513,"firstname":"John","lastname":"McCarthy","knownname":"","position":"Goalkeeper","number":"27","defaultPosition":"Goalkeeper"},"163074":{"side":"Away","team":5513,"firstname":"Ken","lastname":"Tribbett","knownname":"","position":"Defender","number":"4","defaultPosition":"Defender"},"163096":{"side":"Away","team":5513,"firstname":"Walter","lastname":"Restrepo","knownname":"","position":"Midfielder","number":"20","defaultPosition":"Midfielder"},"223658":{"side":"Away","team":5513,"firstname":"Cole","lastname":"Missimo","knownname":"","position":"Midfielder","number":"19","defaultPosition":"Midfielder"},"95321":{"side":"Away","team":5513,"firstname":"Charles","lastname":"Kwabena Sapong","knownname":"C.J. Sapong","position":"Forward","number":"17","defaultPosition":"Forward"},"152294":{"side":"Away","team":5513,"firstname":"Leo","lastname":"Fernandes","knownname":"","position":"Midfielder","number":"22","defaultPosition":"Midfielder"}},"snapshots":[{"timestamp":1467515379,"period":"FullTime","type":"Result","matchTime":97,"players":{"83274":{"stats":[0,0,0,0,0,0,0,0,0,0,0,0,0,0,0,0,0,0,0,0,0,7,1,18,11,2,7,19,0,0,0,0,0,0,0,0,0,0,0,0,0,0,0,1,0,0,0,0,0,0,0,0,0,0,0,0,0,0,2,0,0,0,0,2,1,0,0,0,0,0,1,0,0,0,0,0,8,0,0,1,1,0,0,0,1,0,0,1,2,0,0,0,0],"participation":1,"participationMin":97,"index":{"total":253,"off":68.5,"def":184.5}},"50143":{"stats":[0,0,0,0,0,0,2,0,0,0,0,0,0,0,2,0,1,0,0,0,0,16,2,12,1,3,6,6,0,0,0,0,0,0,2,0,0,0,0,0,0,1,0,2,1,0,0,1,0,0,0,0,0,0,0,0,0,0,0,0,0,0,0,0,0,0,0,0,0,0,1,0,0,0,0,0,1,0,0,0,0,0,0,0,0,0,0,0,0,0,0,0,0],"participation":1,"participationMin":97,"index":{"total":494,"off":383,"def":111}},"12875":{"stats":[0,0,0,0,0,0,0,0,0,0,0,0,0,0,0,0,0,0,0,0,1,13,1,37,7,14,7,7,0,2,0,0,0,0,0,3,0,1,1,0,0,1,0,6,0,0,0,0,1,0,0,0,0,0,0,0,0,0,0,0,0,0,0,0,0,0,0,0,0,0,1,0,0,0,0,1,6,0,0,0,0,0,0,0,0,0,0,0,0,0,0,0,0],"participation":1,"participationMin":97,"index":{"total":481,"off":189,"def":292}},"90116":{"stats":[0,0,0,0,0,0,0,1,0,0,0,0,0,0,0,1,0,0,0,0,0,29,1,17,6,3,5,10,1,0,0,2,0,0,2,0,0,1,1,0,0,3,0,3,1,1,0,3,0,0,0,0,0,0,0,0,0,0,0,0,0,0,0,0,0,0,0,0,0,0,1,0,0,0,0,0,3,0,0,0,0,0,0,0,0,0,0,0,0,0,0,0,0],"participation":1,"participationMin":97,"index":{"total":222,"off":54,"def":168}},"95228":{"stats":[0,0,0,0,0,0,0,0,0,0,0,0,0,0,0,0,0,0,0,0,3,14,4,31,12,11,2,9,3,6,0,0,0,0,3,1,0,1,0,0,0,1,0,0,0,0,0,0,0,0,0,0,0,0,0,0,0,0,0,0,0,0,0,0,0,0,0,0,0,0,1,0,0,0,0,3,6,0,0,0,0,0,0,0,0,0,0,0,0,0,0,0,0],"participation":1,"participationMin":97,"index":{"total":156,"off":104.5,"def":51.5}},"20568":{"stats":[0,0,0,0,0,0,1,0,0,0,0,2,0,0,1,0,0,0,0,0,1,7,2,23,10,8,0,1,1,5,4,0,1,1,3,0,0,2,0,0,0,0,0,1,4,2,0,1,1,0,0,0,0,0,0,0,0,0,0,0,0,0,0,0,0,0,0,0,0,0,0,0,0,0,0,0,4,0,0,0,0,0,0,0,0,0,0,0,0,0,0,0,0],"participation":0.8659793814433,"participationMin":84,"index":{"total":431,"off":352.5,"def":78.5}},"83072":{"stats":[0,0,0,0,0,0,0,0,0,0,0,0,1,0,0,0,0,0,0,0,1,13,1,21,7,6,5,8,0,1,0,1,0,0,1,0,0,1,1,0,2,0,0,3,2,0,0,0,0,0,0,0,0,0,0,0,0,0,0,0,0,0,0,0,0,0,0,0,0,0,0,0,0,0,0,1,5,0,0,0,0,0,0,0,0,0,0,0,0,0,0,0,0],"participation":1,"participationMin":97,"index":{"total":248,"off":101,"def":147}},"55209":{"stats":[0,0,0,0,0,0,0,1,0,0,1,0,0,0,0,0,0,0,0,0,1,5,3,35,1,18,2,2,0,0,1,0,0,0,4,0,2,2,0,0,0,0,0,0,0,0,1,0,4,0,0,0,0,0,0,0,0,0,0,0,0,0,0,0,0,0,0,0,0,0,1,0,0,0,0,1,3,0,0,0,0,0,0,0,0,0,0,0,0,0,0,0,0],"participation":1,"participationMin":97,"index":{"total":510,"off":468.5,"def":41.5}},"108216":{"stats":[0,0,0,0,0,0,0,0,0,0,0,0,0,0,0,0,0,0,0,0,3,7,2,27,9,5,3,5,4,6,1,0,1,2,3,1,2,2,0,0,0,0,0,0,0,1,0,1,1,0,0,0,0,0,0,0,0,0,0,0,0,0,0,0,0,0,0,0,0,0,0,0,0,0,0,2,5,0,0,0,0,0,0,0,0,0,0,0,0,0,0,0,0],"participation":0.71134020618557,"participationMin":69,"index":{"total":331,"off":300,"def":31}},"33823":{"stats":[0,0,0,0,0,0,0,0,0,0,0,0,0,0,0,0,0,0,0,0,1,9,2,22,2,13,4,5,0,0,0,0,0,0,4,0,1,2,0,0,0,1,0,1,0,0,0,0,0,0,0,0,0,0,0,0,0,0,0,0,0,0,0,0,0,0,0,0,0,0,1,0,0,0,0,1,5,0,0,0,0,0,0,0,0,0,0,0,0,0,0,0,0],"participation":1,"participationMin":97,"index":{"total":246,"off":143.5,"def":102.5}},"95272":{"stats":[0,0,0,0,0,0,2,1,0,0,0,0,0,0,2,1,0,0,0,0,1,2,0,8,2,4,0,0,0,0,1,0,0,0,1,0,1,0,0,0,0,0,0,0,1,0,0,1,0,0,0,0,0,0,0,0,0,0,0,0,0,0,0,0,0,0,0,0,0,0,0,0,0,0,0,1,0,0,0,0,0,0,0,0,0,0,0,0,0,0,0,0,0],"participation":0.61855670103093,"participationMin":60,"index":{"total":485,"off":496,"def":-11}},"78016":{"stats":[0,0,0,0,0,0,0,0,0,0,0,0,0,0,0,0,0,0,0,0,0,0,0,0,0,0,0,0,0,0,0,0,0,0,0,0,0,0,0,0,0,0,0,0,0,0,0,0,0,0,0,0,0,0,0,0,0,0,0,0,0,0,0,0,0,0,0,0,0,0,0,0,0,0,0,0,0,0,0,0,0,0,0,0,0,0,0,0,0,0,0,0,0],"participation":0,"participationMin":0,"index":{"total":0,"off":0,"def":0}},"49541":{"stats":[0,0,0,0,1,0,1,0,0,1,0,0,2,0,0,0,0,0,0,0,1,3,0,27,3,16,3,3,1,2,1,0,1,1,1,0,0,0,0,0,0,0,0,1,0,0,0,1,0,0,1,0,0,0,0,0,0,0,0,0,0,0,0,0,0,0,0,0,0,0,0,0,0,0,0,0,2,0,0,0,0,0,0,0,0,0,0,0,0,0,0,1,0],"participation":0.28865979381443,"participationMin":28,"index":{"total":932,"off":939,"def":-7}},"20086":{"stats":[0,0,0,0,0,0,0,0,0,0,0,0,0,0,0,0,0,0,0,0,0,0,0,0,0,0,0,0,0,0,0,0,0,0,0,0,0,0,0,0,0,0,0,0,0,0,0,0,0,0,0,0,0,0,0,0,0,0,0,0,0,0,0,0,0,0,0,0,0,0,0,0,0,0,0,0,0,0,0,0,0,0,0,0,0,0,0,0,0,0,0,0,0],"participation":0,"participationMin":0,"index":{"total":0,"off":0,"def":0}},"95309":{"stats":[0,0,0,0,0,0,0,0,0,0,0,0,0,0,0,0,0,0,0,0,0,0,0,0,0,0,0,0,0,0,0,0,0,0,0,0,0,0,0,0,0,0,0,0,0,0,0,0,0,0,0,0,0,0,0,0,0,0,0,0,0,0,0,0,0,0,0,0,0,0,0,0,0,0,0,0,0,0,0,0,0,0,0,0,0,0,0,0,0,0,0,0,0],"participation":0,"participationMin":0,"index":{"total":0,"off":0,"def":0}},"87946":{"stats":[0,0,0,0,0,0,0,0,0,0,0,0,0,0,0,0,0,0,0,0,0,2,0,0,0,0,0,0,0,0,0,0,0,0,0,0,0,0,0,0,0,0,0,0,0,0,0,0,0,0,0,0,0,0,0,0,0,0,0,0,0,0,0,0,0,0,0,0,0,0,0,0,0,0,0,0,1,0,0,0,0,0,0,0,0,0,0,0,0,0,0,0,0],"participation":0,"participationMin":0,"index":{"total":6,"off":3,"def":3}},"177658":{"stats":[0,0,0,0,0,0,0,2,0,0,0,0,0,0,0,0,0,0,0,0,2,0,0,7,3,2,0,0,0,0,0,0,0,0,3,0,0,0,0,0,1,0,0,0,0,1,0,0,1,0,0,0,0,0,0,0,0,0,0,0,0,0,0,0,0,0,0,0,0,0,0,0,0,0,0,2,2,0,0,0,0,0,0,0,0,0,0,0,0,0,0,0,0],"participation":0.38144329896907,"participationMin":37,"index":{"total":255,"off":227,"def":28}},"110633":{"stats":[0,0,0,0,0,0,0,0,0,0,0,0,0,0,0,0,0,0,0,0,0,0,0,4,1,3,0,0,0,1,0,0,0,0,0,0,0,0,0,0,0,0,0,0,0,0,0,0,0,0,0,0,0,0,0,0,0,0,0,0,0,0,0,0,0,0,0,0,0,0,0,0,0,0,0,0,0,0,0,0,0,0,0,0,0,0,0,0,0,0,0,0,0],"participation":0.1340206185567,"participationMin":13,"index":{"total":8,"off":8,"def":0}},"163906":{"stats":[0,0,0,0,0,0,0,0,0,0,0,0,0,0,0,0,0,0,0,0,0,9,3,14,11,1,3,14,0,0,0,2,0,0,6,0,0,1,0,0,0,3,0,0,0,0,0,0,0,0,0,0,0,0,0,0,1,5,1,0,0,2,0,10,0,0,0,0,0,0,0,0,0,0,1,0,20,0,0,3,2,0,1,0,2,1,2,1,6,0,0,0,0],"participation":1,"participationMin":97,"index":{"total":991,"off":91.5,"def":899.5}},"132000":{"stats":[0,0,0,0,0,0,0,0,0,0,0,0,0,0,0,0,0,0,0,0,0,9,5,18,8,3,1,3,0,0,0,2,0,0,4,0,0,2,0,0,2,0,1,1,2,4,1,1,0,0,0,0,0,0,0,0,1,0,0,0,0,0,0,0,0,0,0,0,0,0,0,0,0,0,0,0,3,0,0,0,0,0,0,0,0,0,0,0,0,0,0,0,0],"participation":1,"participationMin":97,"index":{"total":-19,"off":-156.5,"def":137.5}},"202192":{"stats":[0,0,0,0,0,0,0,0,0,0,0,0,0,0,0,0,0,0,0,0,0,30,1,18,4,1,9,10,0,0,0,0,0,0,0,0,0,1,0,0,3,2,0,2,0,0,0,2,0,0,0,0,0,0,1,0,0,0,0,0,0,0,0,0,0,0,0,0,0,1,0,0,0,0,0,0,4,0,0,0,0,0,0,0,0,0,0,0,0,0,0,0,0],"participation":1,"participationMin":97,"index":{"total":-274,"off":-281.5,"def":7.5}},"127541":{"stats":[0,0,0,0,0,0,0,0,0,0,0,0,0,0,0,0,0,0,0,0,1,20,4,23,9,7,4,7,0,3,1,0,0,0,4,0,0,0,0,0,0,0,0,2,0,0,2,1,0,0,0,0,0,0,0,0,1,0,0,0,0,0,0,0,0,0,0,0,0,0,0,0,0,0,0,1,3,0,0,0,0,0,0,0,0,0,0,0,0,0,0,0,0],"participation":1,"participationMin":97,"index":{"total":-86,"off":-22.5,"def":-63.5}},"178000":{"stats":[0,0,0,0,0,0,0,0,0,0,0,0,0,0,0,0,0,0,0,0,0,27,1,17,7,0,9,12,0,0,0,2,0,0,1,0,0,1,1,0,3,4,0,3,1,1,0,0,1,0,0,0,0,0,0,0,1,0,0,0,0,0,0,0,0,0,0,0,0,0,0,0,0,0,0,0,3,0,0,0,0,0,0,0,0,0,0,0,0,0,0,0,0],"participation":1,"participationMin":97,"index":{"total":403,"off":14,"def":389}},"86574":{"stats":[0,0,0,0,0,0,0,0,0,0,0,0,1,0,0,0,0,0,0,0,0,2,0,8,4,4,0,0,0,0,0,0,0,0,0,0,1,0,0,0,0,0,0,0,1,0,0,0,2,0,0,0,1,0,0,0,0,0,0,0,0,0,0,0,0,0,0,0,0,0,0,0,0,0,0,0,1,0,0,0,0,0,0,0,0,0,0,0,0,0,0,0,0],"participation":0.64948453608247,"participationMin":63,"index":{"total":28,"off":-2.5,"def":30.5}},"28091":{"stats":[0,0,0,0,0,0,0,0,0,0,0,0,0,0,0,0,0,0,0,0,0,23,2,20,4,5,2,3,0,0,0,0,0,0,1,0,0,2,1,0,0,1,0,0,0,0,0,2,0,0,1,0,1,0,0,0,1,0,0,0,0,0,0,0,0,0,0,0,0,0,0,0,0,0,0,0,0,0,0,0,0,0,0,0,0,0,0,0,0,0,0,0,0],"participation":1,"participationMin":97,"index":{"total":21,"off":-4.5,"def":25.5}},"18094":{"stats":[0,0,0,0,0,0,0,0,0,0,1,0,0,0,0,0,0,0,0,0,3,11,0,28,9,7,2,2,5,3,1,0,2,1,1,0,0,0,0,0,0,0,0,0,0,0,1,0,1,0,0,0,1,0,0,0,0,0,0,0,0,0,0,0,0,0,0,0,0,0,0,0,0,0,0,2,5,0,0,0,0,0,0,0,0,0,0,0,0,0,0,0,0],"participation":0.90721649484536,"participationMin":88,"index":{"total":544,"off":549,"def":-5}},"110575":{"stats":[0,0,0,0,0,0,0,0,0,0,0,1,0,0,0,0,0,0,0,0,0,16,1,24,5,6,2,5,0,0,0,0,0,0,6,0,0,2,0,0,0,0,0,2,1,0,0,2,1,0,0,0,0,1,0,0,1,0,0,0,0,0,0,0,0,0,0,0,0,0,0,0,0,0,0,0,7,0,0,0,0,0,0,0,0,0,0,0,0,0,0,0,0],"participation":1,"participationMin":97,"index":{"total":87,"off":27,"def":60}},"45120":{"stats":[0,0,0,0,0,0,0,0,0,0,0,0,0,0,0,0,0,0,0,0,0,3,2,14,5,7,2,2,0,0,0,0,0,0,1,1,1,2,0,0,0,1,0,2,0,0,0,0,0,0,0,0,0,0,0,0,0,0,0,0,0,0,0,0,0,0,0,0,0,0,0,0,0,0,0,0,4,0,0,0,0,0,0,0,0,0,0,0,0,0,0,0,0],"participation":0.64948453608247,"participationMin":63,"index":{"total":128,"off":5,"def":123}},"60152":{"stats":[0,0,0,0,0,0,0,1,0,0,0,0,0,0,0,1,0,0,0,0,1,2,2,16,2,8,1,2,0,0,1,1,0,0,2,0,2,0,0,0,0,1,0,0,0,1,0,0,1,0,0,0,0,0,0,0,1,0,0,0,0,0,0,0,0,0,0,0,0,0,0,0,0,0,0,1,1,0,0,0,0,0,0,0,0,0,0,0,0,0,0,0,0],"participation":1,"participationMin":97,"index":{"total":190,"off":183.5,"def":6.5}},"110974":{"stats":[0,0,0,0,0,0,0,0,0,0,0,0,0,0,0,0,0,0,0,0,0,0,0,0,0,0,0,0,0,0,0,0,0,0,0,0,0,0,0,0,0,0,0,0,0,0,0,0,0,0,0,0,0,0,0,0,0,0,0,0,0,0,0,0,0,0,0,0,0,0,0,0,0,0,0,0,0,0,0,0,0,0,0,0,0,0,0,0,0,0,0,0,0],"participation":0,"participationMin":0,"index":{"total":0,"off":0,"def":0}},"163565":{"stats":[0,0,0,0,0,0,0,0,0,0,0,0,0,0,0,0,0,0,0,0,0,0,0,0,0,0,0,0,0,0,0,0,0,0,0,0,0,0,0,0,0,0,0,0,0,0,0,0,0,0,0,0,0,0,0,0,0,0,0,0,0,0,0,0,0,0,0,0,0,0,0,0,0,0,0,0,0,0,0,0,0,0,0,0,0,0,0,0,0,0,0,0,0],"participation":0,"participationMin":0,"index":{"total":0,"off":0,"def":0}},"163074":{"stats":[0,0,0,0,0,0,0,0,0,0,0,0,0,0,0,0,0,0,0,0,0,0,0,3,1,1,2,2,0,0,0,0,0,0,0,0,0,0,0,0,0,0,0,0,0,0,0,0,0,0,0,0,0,0,0,0,1,0,0,0,0,0,0,0,0,0,0,0,0,0,0,0,0,0,0,0,0,0,0,0,0,0,0,0,0,0,0,0,0,0,0,0,0],"participation":0.092783505154639,"participationMin":9,"index":{"total":4,"off":4,"def":0}},"163096":{"stats":[0,0,0,0,0,0,0,0,0,0,0,0,0,0,0,0,0,0,0,0,0,0,0,0,0,0,0,0,0,0,0,0,0,0,0,0,0,0,0,0,0,0,0,0,0,0,0,0,0,0,0,0,0,0,0,0,0,0,0,0,0,0,0,0,0,0,0,0,0,0,0,0,0,0,0,0,0,0,0,0,0,0,0,0,0,0,0,0,0,0,0,0,0],"participation":0,"participationMin":0,"index":{"total":0,"off":0,"def":0}},"223658":{"stats":[0,0,0,0,0,0,0,0,0,0,0,0,0,0,0,0,0,0,0,0,0,0,0,0,0,0,0,0,0,0,0,0,0,0,0,0,0,0,0,0,0,0,0,0,0,0,0,0,0,0,0,0,0,0,0,0,0,0,0,0,0,0,0,0,0,0,0,0,0,0,0,0,0,0,0,0,0,0,0,0,0,0,0,0,0,0,0,0,0,0,0,0,0],"participation":0,"participationMin":0,"index":{"total":0,"off":0,"def":0}},"95321":{"stats":[0,0,0,0,0,0,0,0,1,0,1,0,0,0,0,0,0,0,0,0,0,1,0,6,3,2,1,1,0,1,0,1,0,0,0,0,1,0,0,0,0,0,0,0,0,2,0,0,1,0,0,0,1,0,0,0,1,0,0,0,0,0,0,0,0,0,0,0,0,0,0,0,0,0,0,0,0,0,0,0,0,0,0,0,0,0,0,0,0,0,0,0,0],"participation":0.35051546391753,"participationMin":34,"index":{"total":148,"off":156.5,"def":-8.5}},"152294":{"stats":[0,0,0,0,0,0,0,0,1,0,0,0,0,0,0,0,0,0,0,0,0,2,1,9,5,2,1,3,0,0,0,0,0,0,1,0,0,0,0,0,0,0,0,1,0,1,1,1,0,0,0,0,0,0,0,0,1,0,0,0,0,0,0,0,0,0,0,0,0,0,0,0,0,0,0,0,2,0,0,0,0,0,0,0,0,0,0,0,0,0,0,0,0],"participation":0.35051546391753,"participationMin":34,"index":{"total":-77,"off":-38.5,"def":-38.5}}},"score_Home":1,"score_Away":0,"running":false,"progress":5820,"sinceMatchBegin":7144,"f9Id":234794,"F24Id":234792,"goals":{"0":{"pID":49541,"tID":1897,"order":2094048,"own":false},"score_home":1,"score_away":0,"last_home":{"pID":49541,"tID":1897,"order":2094048,"own":false},"last_away":null},"relevance":100,"halfscore_Home":0,"halfscore_Away":0}],"range":{"from":null,"till":null}}}