{"status":"success","match":{"competitionId":98,"seasonId":2017,"matchId":902298,"first_half_start":1498873197,"first_half_stop":1498875962,"second_half_start":1498876879,"second_half_stop":1498879781,"date":1498872600,"teams":{"Home":{"id":1899,"name":"Real Salt Lake"},"Away":{"id":6900,"name":"Orlando City SC"}},"statIndexes":{"hit_woodwork":0,"att_pen_goal":1,"att_pen_target":2,"att_pen_off_target":3,"direct_goals":4,"att_ibox_goal":5,"att_ibox_target":6,"att_ibox_off_target":7,"att_ibox_blocked":8,"att_obox_goal":9,"att_obox_target":10,"att_obox_off_target":11,"att_obox_blocked":12,"att_hd_goal":13,"att_hd_target":14,"att_hd_off_target":15,"ShotsClearedoffLineInsideBox_F24":16,"ShotsClearedoffLineOutsideBox_F24":17,"own_goals":18,"goal_assist":19,"key_passes":20,"accurate_back_zone_pass":21,"failed_back_zone_pass":22,"total_fwd_zone_pass":23,"failed_fwd_zone_pass":24,"successful_final_third_passes":25,"long_pass_own_to_opp_success":26,"long_pass_own_to_opp":27,"accurate_cross":28,"failed_cross":29,"won_corners":30,"lost_corners":31,"accurate_corners_intobox":32,"failed_corners_intobox":33,"OutofPlayConceded_F24":34,"won_contest":35,"lost_contest":36,"won_tackle":37,"lost_tackle":38,"last_man_tackle":39,"head_clearance":40,"nohead_clearance":41,"clearance_off_line":42,"interception":43,"aerial_won":44,"aerial_lost":45,"challenge_lost":46,"fouls":47,"was_fouled":48,"penalty_won":49,"hand_ball":50,"penalty_conceded":51,"total_offside":52,"yellow_card":53,"red_card":54,"goals_conceded_ibox":55,"goals_conceded_obox":56,"saved_ibox":57,"saved_obox":58,"penalty_save":59,"good_high_claim":60,"punches":61,"drops":62,"accurate_keeper_throws":63,"failed_keeper_throws":64,"six_yard_block":65,"total_attacking_pass":66,"error_lead_to_goal":67,"error_lead_to_shot":68,"second_yellow":69,"clean_sheet":70,"clean_sheet_part":71,"goal_assist_openplay":72,"clean_sheet_away":73,"gk_smother":74,"key_passes_open_play":75,"ball_recovery":76,"shield_ball_oop":77,"accurate_through_ball":78,"SavesDiving_F24":79,"SavesStanding_F24":80,"SavesStooping_F24":81,"SavesReaching_F24":82,"SavesFingertip_F24":83,"SavesCaught_F24":84,"SavesCollected_F24":85,"SavesParriedSafe_F24":86,"SavesParriedDanger_F24":87,"SavesHands_F24":88,"SavesFeet_F24":89,"SavesBody_F24":90,"Matchwinner_Goal":91,"Equalizer_Goal":92,"att_pen_miss":93,"att_pen_post":94,"goals":95,"goals_openplay":96,"att_ibox_miss":97,"att_ibox_post":98,"att_obox_miss":99,"att_obox_post":100,"att_hd_miss":101,"att_hd_post":102,"att_ibox_own_goal":103,"att_obox_own_goal":104,"total_att_assist":105,"total_back_zone_pass":106,"accurate_fwd_zone_pass":107,"total_cross":108,"total_corners_intobox":109,"total_contest":110,"total_tackle":111,"total_clearance":112,"total_high_claim":113,"keeper_throws":114,"att_assist_openplay":115},"players":{"15310":{"side":"Home","team":1899,"firstname":"Nick","lastname":"Rimando","knownname":"","position":"Goalkeeper","number":"18","defaultPosition":"Goalkeeper"},"220877":{"side":"Home","team":1899,"firstname":"Danilo","lastname":"Acosta","knownname":"","position":"Defender","number":"25","defaultPosition":"Midfielder"},"50143":{"side":"Home","team":1899,"firstname":"David","lastname":"Horst","knownname":"","position":"Defender","number":"4","defaultPosition":"Defender"},"41606":{"side":"Home","team":1899,"firstname":"Chris","lastname":"Wingert","knownname":"","position":"Defender","number":"16","defaultPosition":"Defender"},"183390":{"side":"Home","team":1899,"firstname":"Justen","lastname":"Glad","knownname":"","position":"Defender","number":"15","defaultPosition":"Defender"},"196666":{"side":"Home","team":1899,"firstname":"Jefferson","lastname":"Savarino","knownname":"","position":"Midfielder","number":"7","defaultPosition":"Forward"},"95278":{"side":"Home","team":1899,"firstname":"Joao","lastname":"Plata","knownname":"","position":"Midfielder","number":"10","defaultPosition":"Forward"},"43684":{"side":"Home","team":1899,"firstname":"Stephen Obayan","lastname":"Sunday","knownname":"Sunny","position":"Midfielder","number":"8","defaultPosition":"Midfielder"},"178386":{"side":"Home","team":1899,"firstname":"Brooks","lastname":"Lennon","knownname":"","position":"Midfielder","number":"27","defaultPosition":"Midfielder"},"15517":{"side":"Home","team":1899,"firstname":"Kyle","lastname":"Beckerman","knownname":"","position":"Midfielder","number":"5","defaultPosition":"Midfielder"},"110624":{"side":"Home","team":1899,"firstname":"Luis","lastname":"Silva","knownname":"","position":"Forward","number":"20","defaultPosition":"Forward"},"84481":{"side":"Home","team":1899,"firstname":"Albert","lastname":"Rusn\u00e1k","knownname":"","position":"Midfielder","number":"11","defaultPosition":"Midfielder"},"116973":{"side":"Home","team":1899,"firstname":"Matt","lastname":"Van Oekel","knownname":"","position":"Goalkeeper","number":"24","defaultPosition":"Goalkeeper"},"78019":{"side":"Home","team":1899,"firstname":"Aaron","lastname":"Maund","knownname":"","position":"Defender","number":"21","defaultPosition":"Defender"},"194187":{"side":"Home","team":1899,"firstname":"Sebasti\u00e1n","lastname":"Saucedo","knownname":"","position":"Midfielder","number":"23","defaultPosition":"Midfielder"},"50136":{"side":"Home","team":1899,"firstname":"Tony","lastname":"Beltran","knownname":"","position":"Defender","number":"2","defaultPosition":"Defender"},"153453":{"side":"Home","team":1899,"firstname":"Luke","lastname":"Mulholland","knownname":"","position":"Midfielder","number":"19","defaultPosition":"Midfielder"},"41535":{"side":"Home","team":1899,"firstname":"Yura","lastname":"Movsisyan","knownname":"","position":"Forward","number":"14","defaultPosition":"Forward"},"95611":{"side":"Away","team":6900,"firstname":"Joe","lastname":"Bendik","knownname":"","position":"Goalkeeper","number":"1","defaultPosition":"Goalkeeper"},"201031":{"side":"Away","team":6900,"firstname":"Jos\u00e9","lastname":"Aja","knownname":"","position":"Defender","number":"4","defaultPosition":"Defender"},"96201":{"side":"Away","team":6900,"firstname":"Donny","lastname":"Toia","knownname":"","position":"Defender","number":"25","defaultPosition":"Defender"},"18005":{"side":"Away","team":6900,"firstname":"Jonathan","lastname":"Spector","knownname":"","position":"Defender","number":"2","defaultPosition":"Defender"},"27678":{"side":"Away","team":6900,"firstname":"Scott","lastname":"Sutter","knownname":"","position":"Defender","number":"21","defaultPosition":"Defender"},"39276":{"side":"Away","team":6900,"firstname":"Will","lastname":"Johnson","knownname":"","position":"Midfielder","number":"8","defaultPosition":"Midfielder"},"149674":{"side":"Away","team":6900,"firstname":"Cristian","lastname":"Higuita","knownname":"","position":"Midfielder","number":"7","defaultPosition":"Midfielder"},"13135":{"side":"Away","team":6900,"firstname":"Ricardo Izecson","lastname":"Dos Santos Leite","knownname":"Kak\u00e1","position":"Midfielder","number":"10","defaultPosition":"Midfielder"},"28573":{"side":"Away","team":6900,"firstname":"Antonio","lastname":"Nocerino","knownname":"","position":"Midfielder","number":"23","defaultPosition":"Midfielder"},"185126":{"side":"Away","team":6900,"firstname":"Cyle","lastname":"Larin","knownname":"","position":"Forward","number":"9","defaultPosition":"Forward"},"20568":{"side":"Away","team":6900,"firstname":"Giles","lastname":"Barnes","knownname":"","position":"Forward","number":"14","defaultPosition":"Forward"},"181180":{"side":"Away","team":6900,"firstname":"Rafael Ant\u00f3nio","lastname":"Figueiredo Ramos","knownname":"Rafael Ramos","position":"Defender","number":"27","defaultPosition":"Defender"},"56790":{"side":"Away","team":6900,"firstname":"Josh","lastname":"Saunders","knownname":"","position":"Goalkeeper","number":"28","defaultPosition":"Goalkeeper"},"221403":{"side":"Away","team":6900,"firstname":"Richie","lastname":"Laryea","knownname":"","position":"Midfielder","number":"6","defaultPosition":"Midfielder"},"83073":{"side":"Away","team":6900,"firstname":"Luis","lastname":"Gil","knownname":"","position":"Midfielder","number":"17","defaultPosition":"Midfielder"},"220442":{"side":"Away","team":6900,"firstname":"Hadji","lastname":"Barry","knownname":"","position":"Midfielder","number":"13","defaultPosition":"Midfielder"},"181013":{"side":"Away","team":6900,"firstname":"Tommy","lastname":"Redding","knownname":"","position":"Defender","number":"29","defaultPosition":"Defender"},"95259":{"side":"Away","team":6900,"firstname":"Servando","lastname":"Carrasco","knownname":"","position":"Midfielder","number":"5","defaultPosition":"Midfielder"}},"snapshots":[{"timestamp":1498879998,"period":"FullTime","type":"Result","matchTime":94,"players":{"15310":{"stats":[0,0,0,0,0,0,0,0,0,0,0,0,0,0,0,0,0,0,0,0,1,17,0,5,2,1,3,5,0,0,0,1,0,0,0,0,0,0,0,0,0,0,0,0,0,0,0,0,1,0,0,0,0,0,0,1,0,1,2,0,0,0,0,5,0,0,0,0,0,0,0,0,0,0,0,1,10,0,0,1,2,0,0,0,0,2,1,0,3,0,0,0,0],"participation":1,"participationMin":94,"index":{"total":315.75,"off":109.75,"def":206}},"220877":{"stats":[0,0,0,0,0,0,0,0,0,0,0,0,0,0,0,0,0,0,0,0,1,10,6,29,9,9,4,7,0,2,0,0,0,0,3,1,1,2,0,0,0,0,0,1,0,4,2,0,2,0,0,0,0,0,0,1,0,0,0,0,0,0,0,0,0,0,0,0,0,0,0,0,0,0,0,1,6,0,0,0,0,0,0,0,0,0,0,0,0,0,0,0,0],"participation":1,"participationMin":94,"index":{"total":-116.9,"off":-82.9,"def":-34}},"50143":{"stats":[0,0,0,0,0,0,0,0,0,0,0,0,0,0,0,0,0,0,0,0,0,33,3,18,7,4,10,14,0,0,0,1,0,0,1,0,0,2,0,0,1,0,0,0,5,1,0,2,0,0,0,0,0,0,0,1,0,0,0,0,0,0,0,0,0,0,0,0,0,0,0,0,0,0,0,0,3,2,0,0,0,0,0,0,0,0,0,0,0,0,0,0,0],"participation":1,"participationMin":94,"index":{"total":254.75,"off":28.625,"def":226.125}},"41606":{"stats":[0,0,0,0,0,0,0,0,0,0,0,0,0,0,0,0,0,0,0,0,0,17,1,35,11,13,4,10,1,1,0,1,0,0,3,0,1,3,0,0,2,1,0,0,1,1,0,2,0,0,0,0,0,0,0,1,0,0,0,0,0,0,0,0,0,0,0,0,0,0,0,0,0,0,0,0,6,0,0,0,0,0,0,0,0,0,0,0,0,0,0,0,0],"participation":0.723404255319149,"participationMin":68,"index":{"total":226.5,"off":-27.875,"def":254.375}},"183390":{"stats":[0,0,0,0,0,0,0,0,0,0,0,0,0,0,0,0,0,0,0,0,0,31,5,10,3,0,5,8,0,0,0,1,0,0,2,0,0,0,1,0,3,2,0,2,1,1,0,1,0,0,0,0,0,0,0,1,0,0,0,0,0,0,0,0,0,0,0,0,0,0,0,0,0,0,0,0,4,0,0,0,0,0,0,0,0,0,0,0,0,0,0,0,0],"participation":1,"participationMin":94,"index":{"total":207.75,"off":-30.875,"def":238.625}},"196666":{"stats":[0,0,0,0,0,0,0,1,0,0,1,0,0,0,0,0,0,0,0,0,1,5,0,26,4,18,1,1,0,0,1,0,0,0,1,0,0,0,0,0,0,0,0,0,0,1,0,1,2,0,1,0,0,0,0,1,0,0,0,0,0,0,0,0,0,0,0,0,0,0,0,0,0,0,0,1,2,0,0,0,0,0,0,0,0,0,0,0,0,0,0,0,0],"participation":1,"participationMin":94,"index":{"total":319.55,"off":334.925,"def":-15.375}},"95278":{"stats":[0,0,0,0,0,0,1,1,1,0,0,1,0,0,0,0,0,0,0,0,3,7,0,47,16,22,2,4,2,7,1,0,0,2,3,4,2,0,0,0,0,0,0,0,0,0,1,1,0,0,0,0,1,0,0,1,0,0,0,0,0,0,0,0,0,0,0,0,0,0,0,0,0,0,0,1,2,0,0,0,0,0,0,0,0,0,0,0,0,0,0,0,0],"participation":1,"participationMin":94,"index":{"total":482.2,"off":520.7,"def":-38.5}},"43684":{"stats":[0,0,0,0,0,0,0,0,0,0,0,0,0,0,0,0,0,0,0,0,0,17,5,35,7,13,9,10,0,0,0,0,0,0,0,0,0,3,1,0,0,0,0,6,0,2,0,3,1,0,0,0,0,1,0,1,0,0,0,0,0,0,0,0,0,0,0,0,0,0,0,0,0,0,0,0,4,0,0,0,0,0,0,0,0,0,0,0,0,0,0,0,0],"participation":0.8829787234042553,"participationMin":83,"index":{"total":141.75,"off":-3.25,"def":145}},"178386":{"stats":[0,0,0,0,0,0,0,1,0,0,0,0,0,0,0,1,0,0,0,0,2,8,3,43,15,19,0,0,0,3,1,0,0,0,5,4,0,0,0,0,0,1,0,0,0,3,0,1,1,0,0,0,4,0,0,1,0,0,0,0,0,0,0,0,0,0,0,0,0,0,0,0,0,0,0,2,4,0,1,0,0,0,0,0,0,0,0,0,0,0,0,0,0],"participation":1,"participationMin":94,"index":{"total":231.70000000000002,"off":247.82500000000002,"def":-16.125}},"15517":{"stats":[0,0,0,0,0,0,0,0,0,0,0,1,0,0,0,0,0,0,0,0,1,25,1,46,12,16,8,14,0,0,0,0,0,0,4,1,0,2,0,0,0,0,0,1,0,2,0,3,3,0,0,0,0,1,0,1,0,0,0,0,0,0,0,0,0,0,0,0,0,0,0,0,0,0,0,1,8,0,0,0,0,0,0,0,0,0,0,0,0,0,0,0,0],"participation":1,"participationMin":94,"index":{"total":171.05,"off":123.30000000000003,"def":47.75}},"110624":{"stats":[0,0,0,0,0,0,0,2,0,0,0,0,0,0,0,1,0,0,0,0,0,6,0,11,6,2,0,0,0,1,1,0,0,0,2,0,1,1,0,0,0,0,0,0,1,1,1,1,1,0,0,0,0,0,0,1,0,0,0,0,0,0,0,0,0,0,0,0,0,0,0,0,0,0,0,0,2,0,0,0,0,0,0,0,0,0,0,0,0,0,0,0,0],"participation":0.8191489361702128,"participationMin":77,"index":{"total":124.1,"off":127.6,"def":-3.5}},"84481":{"stats":[0,0,0,0,0,0,0,0,0,0,0,0,1,0,0,0,0,0,0,0,0,2,0,3,1,1,0,0,0,1,0,0,0,0,0,0,0,0,0,0,0,0,0,1,0,0,0,0,0,0,0,0,0,0,0,0,0,0,0,0,0,0,0,0,0,0,0,0,0,0,0,0,0,0,0,0,0,0,0,0,0,0,0,0,0,0,0,0,0,0,0,0,0],"participation":0.18085106382978725,"participationMin":17,"index":{"total":50,"off":17,"def":33}},"116973":{"stats":[0,0,0,0,0,0,0,0,0,0,0,0,0,0,0,0,0,0,0,0,0,0,0,0,0,0,0,0,0,0,0,0,0,0,0,0,0,0,0,0,0,0,0,0,0,0,0,0,0,0,0,0,0,0,0,0,0,0,0,0,0,0,0,0,0,0,0,0,0,0,0,0,0,0,0,0,0,0,0,0,0,0,0,0,0,0,0,0,0,0,0,0,0],"participation":0,"participationMin":0,"index":{"total":0,"off":0,"def":0}},"78019":{"stats":[0,0,0,0,0,0,0,0,0,0,0,0,0,0,0,0,0,0,0,0,0,0,0,0,0,0,0,0,0,0,0,0,0,0,0,0,0,0,0,0,0,0,0,0,0,0,0,0,0,0,0,0,0,0,0,0,0,0,0,0,0,0,0,0,0,0,0,0,0,0,0,0,0,0,0,0,0,0,0,0,0,0,0,0,0,0,0,0,0,0,0,0,0],"participation":0,"participationMin":0,"index":{"total":0,"off":0,"def":0}},"194187":{"stats":[0,0,0,0,0,0,0,0,0,0,0,0,0,0,0,0,0,0,0,0,0,0,0,3,0,3,0,0,0,0,0,0,0,0,1,0,0,1,0,0,0,0,0,0,0,0,0,0,1,0,0,0,1,0,0,0,0,0,0,0,0,0,0,0,0,0,0,0,0,0,0,0,0,0,0,0,1,0,0,0,0,0,0,0,0,0,0,0,0,0,0,0,0],"participation":0.11702127659574468,"participationMin":11,"index":{"total":62.5,"off":19.5,"def":43}},"50136":{"stats":[0,0,0,0,0,0,0,0,0,0,0,0,0,0,0,0,0,0,0,0,0,0,0,0,0,0,0,0,0,0,0,0,0,0,0,0,0,0,0,0,0,0,0,0,0,0,0,0,0,0,0,0,0,0,0,0,0,0,0,0,0,0,0,0,0,0,0,0,0,0,0,0,0,0,0,0,0,0,0,0,0,0,0,0,0,0,0,0,0,0,0,0,0],"participation":0,"participationMin":0,"index":{"total":0,"off":0,"def":0}},"153453":{"stats":[0,0,0,0,0,0,0,0,0,0,0,0,0,0,0,0,0,0,0,0,0,0,0,0,0,0,0,0,0,0,0,0,0,0,0,0,0,0,0,0,0,0,0,0,0,0,0,0,0,0,0,0,0,0,0,0,0,0,0,0,0,0,0,0,0,0,0,0,0,0,0,0,0,0,0,0,0,0,0,0,0,0,0,0,0,0,0,0,0,0,0,0,0],"participation":0,"participationMin":0,"index":{"total":0,"off":0,"def":0}},"41535":{"stats":[0,0,0,0,0,0,0,0,0,0,0,0,0,0,0,0,0,0,0,0,0,0,0,3,2,1,0,0,0,0,0,0,0,0,0,0,0,1,0,0,1,0,0,0,0,1,0,0,2,0,0,0,0,0,0,0,0,0,0,0,0,0,0,0,0,0,0,0,0,0,0,0,0,0,0,0,0,0,0,0,0,0,0,0,0,0,0,0,0,0,0,0,0],"participation":0.2765957446808511,"participationMin":26,"index":{"total":71,"off":13,"def":58}},"95611":{"stats":[0,0,0,0,0,0,0,0,0,0,0,0,0,0,0,0,0,0,0,0,0,4,0,37,25,7,12,37,0,0,0,1,0,0,5,0,0,1,0,0,0,1,0,0,0,0,0,0,0,0,0,0,0,0,0,0,0,1,1,0,2,0,0,0,0,0,0,0,0,0,1,0,0,0,1,0,12,0,0,1,1,0,0,0,0,1,1,0,2,0,0,0,0],"participation":1,"participationMin":94,"index":{"total":484.25,"off":127,"def":357.25}},"201031":{"stats":[1,0,0,0,0,0,0,1,0,0,0,0,0,0,0,1,0,0,0,0,0,10,1,8,4,2,4,8,0,0,0,0,0,0,4,0,0,1,1,0,5,3,0,4,1,1,1,2,2,0,0,0,0,1,0,0,0,0,0,0,0,0,0,0,0,0,0,0,0,0,1,0,0,0,0,0,1,0,0,0,0,0,0,0,0,0,0,0,0,0,0,0,0],"participation":1,"participationMin":94,"index":{"total":568.75,"off":82.875,"def":485.875}},"96201":{"stats":[0,0,0,0,0,0,0,0,0,0,0,0,0,0,0,0,0,0,0,0,0,13,2,18,12,2,1,13,0,0,0,1,0,0,6,1,1,2,0,0,4,3,0,5,3,1,2,1,1,0,0,0,0,0,0,0,0,0,0,0,0,0,0,0,0,0,0,0,0,0,1,0,0,0,0,0,9,0,0,0,0,0,0,0,0,0,0,0,0,0,0,0,0],"participation":1,"participationMin":94,"index":{"total":456.25,"off":-121.625,"def":577.875}},"18005":{"stats":[0,0,0,0,0,0,0,0,0,0,0,0,0,0,0,0,0,0,0,0,0,25,4,8,3,1,5,8,0,0,0,0,0,0,2,0,0,0,0,0,2,2,0,4,0,0,0,2,0,0,0,0,0,0,0,0,0,0,0,0,0,0,0,0,0,0,0,0,0,0,1,0,0,0,0,0,3,0,0,0,0,0,0,0,0,0,0,0,0,0,0,0,0],"participation":1,"participationMin":94,"index":{"total":281,"off":-52.5,"def":333.5}},"27678":{"stats":[0,0,0,0,0,0,0,0,0,0,0,0,0,0,0,0,0,0,0,0,0,6,1,14,5,4,3,5,1,1,1,1,0,0,5,0,0,3,0,0,2,4,0,1,2,0,3,1,1,0,0,0,0,0,0,0,0,0,0,0,0,0,0,0,0,0,0,0,0,0,1,0,0,0,0,0,4,0,0,0,0,0,0,0,0,0,0,0,0,0,0,0,0],"participation":1,"participationMin":94,"index":{"total":398.75,"off":52.25,"def":346.5}},"39276":{"stats":[0,0,0,0,1,1,0,0,0,0,1,0,0,0,0,0,0,0,0,0,0,11,1,24,7,8,1,3,0,1,0,1,0,0,2,0,0,1,0,0,0,1,0,1,2,0,1,0,0,0,0,0,0,0,0,0,0,0,0,0,0,0,0,0,0,0,0,0,0,0,1,0,0,0,0,0,2,0,0,0,0,0,0,0,0,0,0,0,0,0,0,1,0],"participation":1,"participationMin":94,"index":{"total":680.75,"off":442.5,"def":238.25}},"149674":{"stats":[0,0,0,0,0,0,0,0,0,0,0,0,0,0,0,0,0,0,0,0,1,18,0,17,5,4,0,1,0,1,0,0,0,0,1,0,0,1,0,0,0,0,0,4,0,0,2,2,4,0,0,0,0,1,0,0,0,0,0,0,0,0,0,0,0,0,0,0,0,0,0,0,0,0,0,1,8,0,0,0,0,0,0,0,0,0,0,0,0,0,0,0,0],"participation":0.9361702127659575,"participationMin":88,"index":{"total":126.95,"off":33.45,"def":93.5}},"13135":{"stats":[0,0,0,0,0,0,0,0,0,0,0,0,0,0,0,0,0,0,0,0,1,11,2,20,4,5,1,1,1,0,0,0,0,0,2,1,1,2,0,0,0,0,0,1,0,0,0,1,2,0,0,0,0,1,0,0,0,0,0,0,0,0,0,0,0,0,0,0,0,0,0,0,0,0,0,1,2,0,0,0,0,0,0,0,0,0,0,0,0,0,0,0,0],"participation":0.7659574468085106,"participationMin":72,"index":{"total":159.45,"off":101.95,"def":57.5}},"28573":{"stats":[0,0,0,0,0,0,0,0,0,0,0,0,0,0,0,0,0,0,0,0,1,10,1,19,4,3,2,2,0,0,0,0,0,0,0,0,0,0,0,0,0,0,0,1,0,0,0,1,1,0,0,0,0,0,0,0,0,0,0,0,0,0,0,0,0,0,0,0,0,0,0,0,0,0,0,1,0,0,0,0,0,0,0,0,0,0,0,0,0,0,0,0,0],"participation":0.4787234042553192,"participationMin":45,"index":{"total":100.45,"off":72.95,"def":27.5}},"185126":{"stats":[0,0,0,0,0,0,0,1,1,0,0,0,0,0,0,0,0,0,0,0,1,3,0,13,2,8,1,1,0,0,1,0,0,0,4,0,1,0,0,0,1,0,0,0,1,2,1,2,2,0,0,0,1,0,0,0,0,0,0,0,0,0,0,0,0,1,0,0,0,0,1,0,0,0,0,1,2,0,0,0,0,0,0,0,0,0,0,0,0,0,0,0,0],"participation":1,"participationMin":94,"index":{"total":-71,"off":-50.49999999999999,"def":-20.5}},"20568":{"stats":[0,0,0,0,0,0,0,0,0,0,1,0,0,0,0,0,0,0,0,0,1,1,1,21,8,7,1,1,0,1,1,0,0,0,5,1,0,2,0,0,0,0,0,1,6,3,0,1,0,0,0,0,0,0,0,0,0,0,0,0,0,0,0,0,0,0,0,0,0,0,1,0,0,0,0,1,1,0,0,0,0,0,0,0,0,0,0,0,0,0,0,0,0],"participation":1,"participationMin":94,"index":{"total":262.85,"off":221.85,"def":41}},"181180":{"stats":[0,0,0,0,0,0,0,0,0,0,0,0,0,0,0,0,0,0,0,0,0,0,0,0,0,0,0,0,0,0,0,0,0,0,0,0,0,0,0,0,0,0,0,0,0,0,0,0,0,0,0,0,0,0,0,0,0,0,0,0,0,0,0,0,0,0,0,0,0,0,0,0,0,0,0,0,0,0,0,0,0,0,0,0,0,0,0,0,0,0,0,0,0],"participation":0,"participationMin":0,"index":{"total":0,"off":0,"def":0}},"56790":{"stats":[0,0,0,0,0,0,0,0,0,0,0,0,0,0,0,0,0,0,0,0,0,0,0,0,0,0,0,0,0,0,0,0,0,0,0,0,0,0,0,0,0,0,0,0,0,0,0,0,0,0,0,0,0,0,0,0,0,0,0,0,0,0,0,0,0,0,0,0,0,0,0,0,0,0,0,0,0,0,0,0,0,0,0,0,0,0,0,0,0,0,0,0,0],"participation":0,"participationMin":0,"index":{"total":0,"off":0,"def":0}},"221403":{"stats":[0,0,0,0,0,0,1,0,0,0,0,0,0,0,0,0,0,0,0,0,0,0,0,0,0,0,0,0,0,0,1,0,0,0,0,1,0,0,0,0,0,0,0,0,0,0,0,0,1,0,0,0,0,0,0,0,0,0,0,0,0,0,0,0,0,0,0,0,0,0,0,0,0,0,0,0,0,0,0,0,0,0,0,0,0,0,0,0,0,0,0,0,0],"participation":0.06382978723404255,"participationMin":6,"index":{"total":209.5,"off":199.5,"def":10}},"83073":{"stats":[0,0,0,0,0,0,0,0,0,0,0,0,0,0,0,0,0,0,0,0,0,2,1,3,0,1,0,0,0,0,0,0,0,0,0,0,0,0,0,0,1,0,0,0,1,1,0,0,0,0,0,0,0,0,0,0,0,0,0,0,0,0,0,0,0,0,0,0,0,0,0,0,0,0,0,0,1,0,0,0,0,0,0,0,0,0,0,0,0,0,0,0,0],"participation":0.23404255319148937,"participationMin":22,"index":{"total":44.5,"off":13.25,"def":31.25}},"220442":{"stats":[0,0,0,0,0,0,0,0,0,0,0,0,0,0,0,0,0,0,0,0,0,0,0,0,0,0,0,0,0,0,0,0,0,0,0,0,0,0,0,0,0,0,0,0,0,0,0,0,0,0,0,0,0,0,0,0,0,0,0,0,0,0,0,0,0,0,0,0,0,0,0,0,0,0,0,0,0,0,0,0,0,0,0,0,0,0,0,0,0,0,0,0,0],"participation":0,"participationMin":0,"index":{"total":0,"off":0,"def":0}},"181013":{"stats":[0,0,0,0,0,0,0,0,0,0,0,0,0,0,0,0,0,0,0,0,0,0,0,0,0,0,0,0,0,0,0,0,0,0,0,0,0,0,0,0,0,0,0,0,0,0,0,0,0,0,0,0,0,0,0,0,0,0,0,0,0,0,0,0,0,0,0,0,0,0,0,0,0,0,0,0,0,0,0,0,0,0,0,0,0,0,0,0,0,0,0,0,0],"participation":0,"participationMin":0,"index":{"total":0,"off":0,"def":0}},"95259":{"stats":[0,0,0,0,0,0,0,0,0,0,0,0,0,0,0,0,0,0,0,0,0,5,1,4,1,2,1,1,0,0,0,0,0,0,2,0,0,2,0,0,0,2,0,1,1,0,0,1,0,0,0,0,0,0,0,0,0,0,0,0,0,0,0,0,0,0,0,0,0,0,0,0,0,0,0,0,0,0,0,0,0,0,0,0,0,0,0,0,0,0,0,0,0],"participation":0.5212765957446809,"participationMin":49,"index":{"total":153.25,"off":-3.375,"def":156.625}}},"score_Home":0,"score_Away":1,"running":false,"progress":5640,"sinceMatchBegin":6801,"F24Id":759607,"goals":{"0":{"pID":39276,"tID":6900,"order":1016019,"own":false},"score_home":0,"score_away":1,"last_home":null,"last_away":{"pID":39276,"tID":6900,"order":1016019,"own":false}},"relevance":100,"halfscore_Home":0,"halfscore_Away":1}],"range":{"from":null,"till":null}}}