{"status":"success","match":{"competitionId":15,"seasonId":2016,"matchId":904608,"first_half_start":1485613886,"first_half_stop":1485616726,"second_half_start":1485617658,"second_half_stop":1485620561,"date":1485237600,"teams":{"Home":{"id":2743,"name":"FC Ingolstadt 04"},"Away":{"id":161,"name":"Hamburger SV"}},"statIndexes":{"hit_woodwork":0,"att_pen_goal":1,"att_pen_target":2,"att_pen_off_target":3,"direct_goals":4,"att_ibox_goal":5,"att_ibox_target":6,"att_ibox_off_target":7,"att_ibox_blocked":8,"att_obox_goal":9,"att_obox_target":10,"att_obox_off_target":11,"att_obox_blocked":12,"att_hd_goal":13,"att_hd_target":14,"att_hd_off_target":15,"ShotsClearedoffLineInsideBox_F24":16,"ShotsClearedoffLineOutsideBox_F24":17,"own_goals":18,"goal_assist":19,"key_passes":20,"accurate_back_zone_pass":21,"failed_back_zone_pass":22,"total_fwd_zone_pass":23,"failed_fwd_zone_pass":24,"successful_final_third_passes":25,"long_pass_own_to_opp_success":26,"long_pass_own_to_opp":27,"accurate_cross":28,"failed_cross":29,"won_corners":30,"lost_corners":31,"accurate_corners_intobox":32,"failed_corners_intobox":33,"OutofPlayConceded_F24":34,"won_contest":35,"lost_contest":36,"won_tackle":37,"lost_tackle":38,"last_man_tackle":39,"head_clearance":40,"nohead_clearance":41,"clearance_off_line":42,"interception":43,"aerial_won":44,"aerial_lost":45,"challenge_lost":46,"fouls":47,"was_fouled":48,"penalty_won":49,"hand_ball":50,"penalty_conceded":51,"total_offside":52,"yellow_card":53,"red_card":54,"goals_conceded_ibox":55,"goals_conceded_obox":56,"saved_ibox":57,"saved_obox":58,"penalty_save":59,"good_high_claim":60,"punches":61,"drops":62,"accurate_keeper_throws":63,"failed_keeper_throws":64,"six_yard_block":65,"total_attacking_pass":66,"error_lead_to_goal":67,"error_lead_to_shot":68,"second_yellow":69,"clean_sheet":70,"clean_sheet_part":71,"goal_assist_openplay":72,"clean_sheet_away":73,"gk_smother":74,"key_passes_open_play":75,"ball_recovery":76,"shield_ball_oop":77,"accurate_through_ball":78,"SavesDiving_F24":79,"SavesStanding_F24":80,"SavesStooping_F24":81,"SavesReaching_F24":82,"SavesFingertip_F24":83,"SavesCaught_F24":84,"SavesCollected_F24":85,"SavesParriedSafe_F24":86,"SavesParriedDanger_F24":87,"SavesHands_F24":88,"SavesFeet_F24":89,"SavesBody_F24":90,"Matchwinner_Goal":91,"Equalizer_Goal":92,"att_pen_miss":93,"att_pen_post":94,"goals":95,"goals_openplay":96,"att_ibox_miss":97,"att_ibox_post":98,"att_obox_miss":99,"att_obox_post":100,"att_hd_miss":101,"att_hd_post":102,"att_ibox_own_goal":103,"att_obox_own_goal":104,"total_att_assist":105,"total_back_zone_pass":106,"accurate_fwd_zone_pass":107,"total_cross":108,"total_corners_intobox":109,"total_contest":110,"total_tackle":111,"total_clearance":112,"total_high_claim":113,"keeper_throws":114,"att_assist_openplay":115},"players":{"44564":{"side":"Home","team":2743,"firstname":"Martin","lastname":"Hansen","knownname":"","position":"Goalkeeper","number":"35","defaultPosition":"Goalkeeper"},"172246":{"side":"Home","team":2743,"firstname":"Florent","lastname":"Hadergjonaj","knownname":"","position":"Defender","number":"33","defaultPosition":"Defender"},"18166":{"side":"Home","team":2743,"firstname":"Marvin","lastname":"Matip","knownname":"","position":"Defender","number":"34","defaultPosition":"Defender"},"74376":{"side":"Home","team":2743,"firstname":"Almog","lastname":"Cohen","knownname":"","position":"Defender","number":"36","defaultPosition":"Defender"},"43808":{"side":"Home","team":2743,"firstname":"Markus","lastname":"Suttner","knownname":"","position":"Defender","number":"29","defaultPosition":"Defender"},"100887":{"side":"Home","team":2743,"firstname":"Mathew","lastname":"Leckie","knownname":"","position":"Midfielder","number":"7","defaultPosition":"Midfielder"},"58638":{"side":"Home","team":2743,"firstname":"Roger","lastname":"de Oliveira Bernardo","knownname":"Roger","position":"Midfielder","number":"8","defaultPosition":"Midfielder"},"90511":{"side":"Home","team":2743,"firstname":"Alfredo","lastname":"Morales","knownname":"","position":"Midfielder","number":"6","defaultPosition":"Midfielder"},"37759":{"side":"Home","team":2743,"firstname":"Romain","lastname":"Br\u00e8gerie","knownname":"","position":"Midfielder","number":"18","defaultPosition":"Midfielder"},"60307":{"side":"Home","team":2743,"firstname":"Pascal","lastname":"Gro\u00df","knownname":"","position":"Forward","number":"10","defaultPosition":"Forward"},"93645":{"side":"Home","team":2743,"firstname":"Dar\u00edo","lastname":"Lezcano","knownname":"","position":"Forward","number":"11","defaultPosition":"Forward"},"98770":{"side":"Home","team":2743,"firstname":"\u00d8rjan","lastname":"Nyland","knownname":"","position":"Goalkeeper","number":"1","defaultPosition":"Goalkeeper"},"84827":{"side":"Home","team":2743,"firstname":"Lukas","lastname":"Hinterseer","knownname":"","position":"Forward","number":"16","defaultPosition":"Forward"},"85457":{"side":"Home","team":2743,"firstname":"Sonny","lastname":"Kittel","knownname":"","position":"Midfielder","number":"21","defaultPosition":"Midfielder"},"182276":{"side":"Home","team":2743,"firstname":"Max","lastname":"Christiansen","knownname":"","position":"Midfielder","number":"19","defaultPosition":"Midfielder"},"118344":{"side":"Home","team":2743,"firstname":"Robert","lastname":"Leipertz","knownname":"","position":"Forward","number":"13","defaultPosition":"Forward"},"110927":{"side":"Home","team":2743,"firstname":"Anthony","lastname":"Jung","knownname":"","position":"Defender","number":"3","defaultPosition":"Defender"},"28634":{"side":"Home","team":2743,"firstname":"Tobias","lastname":"Levels","knownname":"","position":"Defender","number":"28","defaultPosition":"Defender"},"162294":{"side":"Away","team":161,"firstname":"Christian","lastname":"Mathenia","knownname":"","position":"Goalkeeper","number":"31","defaultPosition":"Goalkeeper"},"42573":{"side":"Away","team":161,"firstname":"Mergim","lastname":"Mavraj","knownname":"","position":"Defender","number":"13","defaultPosition":"Defender"},"49318":{"side":"Away","team":161,"firstname":"Lewis","lastname":"Holtby","knownname":"","position":"Defender","number":"8","defaultPosition":"Defender"},"62480":{"side":"Away","team":161,"firstname":"Michael","lastname":"Gregoritsch","knownname":"","position":"Defender","number":"11","defaultPosition":"Defender"},"93282":{"side":"Away","team":161,"firstname":"Bobby","lastname":"Wood","knownname":"","position":"Defender","number":"7","defaultPosition":"Defender"},"49012":{"side":"Away","team":161,"firstname":"Kyriakos","lastname":"Papadopoulos","knownname":"","position":"Midfielder","number":"9","defaultPosition":"Midfielder"},"104215":{"side":"Away","team":161,"firstname":"Filip","lastname":"Kostic","knownname":"","position":"Midfielder","number":"17","defaultPosition":"Midfielder"},"120537":{"side":"Away","team":161,"firstname":"Douglas","lastname":"dos Santos Justino de Melo","knownname":"Douglas Santos","position":"Midfielder","number":"6","defaultPosition":"Midfielder"},"168143":{"side":"Away","team":161,"firstname":"Gian-Luca","lastname":"Waldschmidt","knownname":"","position":"Midfielder","number":"15","defaultPosition":"Midfielder"},"92174":{"side":"Away","team":161,"firstname":"Matthias","lastname":"Ostrzolek","knownname":"","position":"Forward","number":"22","defaultPosition":"Forward"},"110524":{"side":"Away","team":161,"firstname":"Gotoku","lastname":"Sakai","knownname":"","position":"Forward","number":"24","defaultPosition":"Forward"},"228316":{"side":"Away","team":161,"firstname":"Bakery","lastname":"Jatta","knownname":"","position":"Forward","number":"18","defaultPosition":"Forward"},"41273":{"side":"Away","team":161,"firstname":"Nicolai","lastname":"M\u00fcller","knownname":"","position":"Midfielder","number":"27","defaultPosition":"Midfielder"},"233275":{"side":"Away","team":161,"firstname":"Vasilije","lastname":"Janjicic","knownname":"","position":"Midfielder","number":"16","defaultPosition":"Midfielder"},"51932":{"side":"Away","team":161,"firstname":"Tom","lastname":"Mickel","knownname":"","position":"Goalkeeper","number":"36","defaultPosition":"Goalkeeper"},"51935":{"side":"Away","team":161,"firstname":"Dennis","lastname":"Diekmeier","knownname":"","position":"Defender","number":"2","defaultPosition":"Defender"},"180177":{"side":"Away","team":161,"firstname":"Finn","lastname":"Porath","knownname":"","position":"Midfielder","number":"34","defaultPosition":"Midfielder"},"192788":{"side":"Away","team":161,"firstname":"Gideon","lastname":"Jung","knownname":"","position":"Defender","number":"28","defaultPosition":"Defender"}},"snapshots":[{"timestamp":1485620602,"period":"FullTime","type":"Result","matchTime":94,"players":{"44564":{"stats":[0,0,0,0,0,0,0,0,0,0,0,0,0,0,0,0,0,0,0,0,0,0,0,0,0,0,0,0,0,0,0,0,0,0,0,0,0,0,0,0,0,0,0,0,0,0,0,0,0,0,0,0,0,0,0,0,1,0,0,0,0,0,0,0,0,0,0,0,0,0,0,0,0,0,0,0,0,0,0,0,0,0,0,0,0,0,0,0,0,0,0,0,0],"participation":1,"participationMin":94,"index":{"total":-110,"off":0,"def":-110}},"172246":{"stats":[0,0,0,0,0,0,0,0,0,0,0,0,0,0,0,0,0,0,0,0,0,0,0,0,0,0,0,0,0,0,0,0,0,0,0,0,0,0,0,0,0,0,0,0,0,0,0,0,0,0,0,0,0,0,0,0,1,0,0,0,0,0,0,0,0,0,0,0,0,0,0,0,0,0,0,0,0,0,0,0,0,0,0,0,0,0,0,0,0,0,0,0,0],"participation":1,"participationMin":94,"index":{"total":0,"off":0,"def":0}},"18166":{"stats":[0,0,0,0,0,0,0,0,0,0,0,0,0,0,0,0,0,0,0,0,0,0,0,0,0,0,0,0,0,0,0,0,0,0,0,0,0,0,0,0,0,0,0,0,0,0,0,0,0,0,0,0,0,0,0,0,1,0,0,0,0,0,0,0,0,0,0,0,0,0,0,0,0,0,0,0,0,0,0,0,0,0,0,0,0,0,0,0,0,0,0,0,0],"participation":1,"participationMin":94,"index":{"total":0,"off":0,"def":0}},"74376":{"stats":[0,1,0,0,0,0,0,0,0,1,0,0,0,0,0,0,0,0,0,0,0,0,0,0,0,0,0,0,0,0,0,0,0,0,0,0,0,0,0,0,0,0,0,0,0,0,0,0,0,0,0,0,0,0,0,0,1,0,0,0,0,0,0,0,0,0,0,0,0,0,0,0,0,0,0,0,0,0,0,0,0,0,0,0,0,0,0,0,0,0,0,0,0],"participation":1,"participationMin":94,"index":{"total":156,"off":156,"def":0}},"43808":{"stats":[0,0,0,0,0,0,0,0,0,1,0,0,0,0,0,0,0,0,0,0,0,0,0,0,0,0,0,0,0,0,0,0,0,0,0,0,0,0,0,0,0,0,0,0,0,0,0,0,0,0,0,0,0,0,0,0,1,0,0,0,0,0,0,0,0,0,0,0,0,0,0,0,0,0,0,0,0,0,0,0,0,0,0,0,0,0,0,0,0,0,0,0,0],"participation":1,"participationMin":94,"index":{"total":294,"off":294,"def":0}},"100887":{"stats":[0,0,0,0,0,0,0,0,0,0,0,0,0,0,0,0,0,0,0,0,0,0,0,0,0,0,0,0,0,0,0,0,0,0,0,0,0,0,0,0,0,0,0,0,0,0,0,0,0,0,0,0,0,0,0,0,0,0,0,0,0,0,0,0,0,0,0,0,0,0,0,0,0,0,0,0,0,0,0,0,0,0,0,0,0,0,0,0,0,0,0,0,0],"participation":0.45744680851064,"participationMin":43,"index":{"total":0,"off":0,"def":0}},"58638":{"stats":[0,0,0,0,0,0,0,0,0,0,0,0,0,0,0,0,0,0,0,0,0,0,0,0,0,0,0,0,0,0,0,0,0,0,0,0,0,0,0,0,0,0,0,0,0,0,0,0,0,0,0,0,0,0,0,0,1,0,0,0,0,0,0,0,0,0,0,0,0,0,0,0,0,0,0,0,0,0,0,0,0,0,0,0,0,0,0,0,0,0,0,0,0],"participation":1,"participationMin":94,"index":{"total":0,"off":0,"def":0}},"90511":{"stats":[0,0,0,0,0,0,0,0,0,0,0,0,0,0,0,0,0,0,0,0,0,0,0,0,0,0,0,0,0,0,0,0,0,0,0,0,0,0,0,0,0,0,0,0,0,0,0,0,0,0,0,0,0,0,0,0,1,0,0,0,0,0,0,0,0,0,0,0,0,0,0,0,0,0,0,0,0,0,0,0,0,0,0,0,0,0,0,0,0,0,0,0,0],"participation":1,"participationMin":94,"index":{"total":0,"off":0,"def":0}},"37759":{"stats":[0,0,0,0,0,0,0,0,0,0,0,0,0,0,0,0,0,0,0,0,0,0,0,0,0,0,0,0,0,0,0,0,0,0,0,0,0,0,0,0,0,0,0,0,0,0,0,0,0,0,0,0,0,0,0,0,1,0,0,0,0,0,0,0,0,0,0,0,0,0,0,0,0,0,0,0,0,0,0,0,0,0,0,0,0,0,0,0,0,0,0,0,0],"participation":1,"participationMin":94,"index":{"total":0,"off":0,"def":0}},"60307":{"stats":[0,0,0,0,0,1,0,0,0,0,0,0,0,0,0,0,0,0,0,0,0,0,0,0,0,0,0,0,0,0,0,0,0,0,0,0,0,0,0,0,0,0,0,0,0,0,0,0,0,0,0,0,0,0,0,0,1,0,0,0,0,0,0,0,0,0,0,0,0,0,0,0,0,0,0,0,0,0,0,0,0,0,0,0,0,0,0,0,0,0,0,0,0],"participation":0.97872340425532,"participationMin":92,"index":{"total":303,"off":303,"def":0}},"93645":{"stats":[0,0,0,0,0,0,0,0,0,0,0,0,0,0,0,0,0,0,0,0,0,0,0,0,0,0,0,0,0,0,0,0,0,0,0,0,0,0,0,0,0,0,0,0,0,0,0,0,0,0,0,0,0,0,0,0,1,0,0,0,0,0,0,0,0,0,0,0,0,0,0,0,0,0,0,0,0,0,0,0,0,0,0,0,0,0,0,0,0,0,0,0,0],"participation":0.92553191489362,"participationMin":87,"index":{"total":0,"off":0,"def":0}},"98770":{"stats":[0,0,0,0,0,0,0,0,0,0,0,0,0,0,0,0,0,0,0,0,0,0,0,0,0,0,0,0,0,0,0,0,0,0,0,0,0,0,0,0,0,0,0,0,0,0,0,0,0,0,0,0,0,0,0,0,0,0,0,0,0,0,0,0,0,0,0,0,0,0,0,0,0,0,0,0,0,0,0,0,0,0,0,0,0,0,0,0,0,0,0,0,0],"participation":0,"participationMin":0,"index":{"total":0,"off":0,"def":0}},"84827":{"stats":[0,0,0,0,0,0,0,0,0,0,0,0,0,0,0,0,0,0,0,0,0,0,0,0,0,0,0,0,0,0,0,0,0,0,0,0,0,0,0,0,0,0,0,0,0,0,0,0,0,0,0,0,0,0,0,0,0,0,0,0,0,0,0,0,0,0,0,0,0,0,0,0,0,0,0,0,0,0,0,0,0,0,0,0,0,0,0,0,0,0,0,0,0],"participation":0.074468085106383,"participationMin":7,"index":{"total":0,"off":0,"def":0}},"85457":{"stats":[0,0,0,0,0,0,0,0,0,0,0,0,0,0,0,0,0,0,0,0,0,0,0,0,0,0,0,0,0,0,0,0,0,0,0,0,0,0,0,0,0,0,0,0,0,0,0,0,0,0,0,0,0,0,0,0,0,0,0,0,0,0,0,0,0,0,0,0,0,0,0,0,0,0,0,0,0,0,0,0,0,0,0,0,0,0,0,0,0,0,0,0,0],"participation":0,"participationMin":0,"index":{"total":0,"off":0,"def":0}},"182276":{"stats":[0,0,0,0,0,0,0,0,0,0,0,0,0,0,0,0,0,0,0,0,0,0,0,0,0,0,0,0,0,0,0,0,0,0,0,0,0,0,0,0,0,0,0,0,0,0,0,0,0,0,0,0,0,0,0,0,0,0,0,0,0,0,0,0,0,0,0,0,0,0,0,0,0,0,0,0,0,0,0,0,0,0,0,0,0,0,0,0,0,0,0,0,0],"participation":0,"participationMin":0,"index":{"total":0,"off":0,"def":0}},"118344":{"stats":[0,0,0,0,0,0,0,0,0,0,0,0,0,0,0,0,0,0,0,0,0,0,0,0,0,0,0,0,0,0,0,0,0,0,0,0,0,0,0,0,0,0,0,0,0,0,0,0,0,0,0,0,0,0,0,0,0,0,0,0,0,0,0,0,0,0,0,0,0,0,0,0,0,0,0,0,0,0,0,0,0,0,0,0,0,0,0,0,0,0,0,0,0],"participation":0,"participationMin":0,"index":{"total":0,"off":0,"def":0}},"110927":{"stats":[0,0,0,0,0,0,0,0,0,0,0,0,0,0,0,0,0,0,0,0,0,0,0,0,0,0,0,0,0,0,0,0,0,0,0,0,0,0,0,0,0,0,0,0,0,0,0,0,0,0,0,0,0,0,0,0,1,0,0,0,0,0,0,0,0,0,0,0,0,0,0,0,0,0,0,0,0,0,0,0,0,0,0,0,0,0,0,0,0,0,0,0,0],"participation":0.54255319148936,"participationMin":51,"index":{"total":0,"off":0,"def":0}},"28634":{"stats":[0,0,0,0,0,0,0,0,0,0,0,0,0,0,0,0,0,0,0,0,0,0,0,0,0,0,0,0,0,0,0,0,0,0,0,0,0,0,0,0,0,0,0,0,0,0,0,0,0,0,0,0,0,0,0,0,0,0,0,0,0,0,0,0,0,0,0,0,0,0,0,0,0,0,0,0,0,0,0,0,0,0,0,0,0,0,0,0,0,0,0,0,0],"participation":0.021276595744681,"participationMin":2,"index":{"total":0,"off":0,"def":0}},"162294":{"stats":[0,0,0,0,0,0,0,0,0,0,0,0,0,0,0,0,0,0,0,0,0,0,0,0,0,0,0,0,0,0,0,0,0,0,0,0,0,0,0,0,0,0,0,0,0,0,0,0,0,0,0,0,0,0,0,1,2,0,0,0,0,0,0,0,0,0,0,0,0,0,0,0,0,0,0,0,0,0,0,0,0,0,0,0,0,0,0,0,0,0,0,0,0],"participation":1,"participationMin":94,"index":{"total":-295,"off":0,"def":-295}},"42573":{"stats":[0,0,0,0,0,0,0,0,0,0,0,0,0,0,0,0,0,0,0,0,0,0,0,0,0,0,0,0,0,0,0,0,0,0,0,0,0,0,0,0,0,0,0,0,0,0,0,0,0,0,0,0,0,0,0,1,2,0,0,0,0,0,0,0,0,0,0,0,0,0,0,0,0,0,0,0,0,0,0,0,0,0,0,0,0,0,0,0,0,0,0,0,0],"participation":1,"participationMin":94,"index":{"total":0,"off":0,"def":0}},"49318":{"stats":[0,0,0,0,0,0,0,0,0,0,0,0,0,0,0,0,0,0,0,0,0,0,0,0,0,0,0,0,0,0,0,0,0,0,0,0,0,0,0,0,0,0,0,0,0,0,0,0,0,0,0,0,0,0,0,1,2,0,0,0,0,0,0,0,0,0,0,0,0,0,0,0,0,0,0,0,0,0,0,0,0,0,0,0,0,0,0,0,0,0,0,0,0],"participation":1,"participationMin":94,"index":{"total":0,"off":0,"def":0}},"62480":{"stats":[0,0,0,0,0,0,0,0,0,0,0,0,0,0,0,0,0,0,0,0,0,0,0,0,0,0,0,0,0,0,0,0,0,0,0,0,0,0,0,0,0,0,0,0,0,0,0,0,0,0,0,0,0,0,0,1,2,0,0,0,0,0,0,0,0,0,0,0,0,0,0,0,0,0,0,0,0,0,0,0,0,0,0,0,0,0,0,0,0,0,0,0,0],"participation":0.72340425531915,"participationMin":68,"index":{"total":0,"off":0,"def":0}},"93282":{"stats":[0,0,0,0,0,0,0,0,0,0,0,0,0,0,0,0,0,0,0,0,0,0,0,0,0,0,0,0,0,0,0,0,0,0,0,0,0,0,0,0,0,0,0,0,0,0,0,0,0,0,0,0,0,0,0,1,2,0,0,0,0,0,0,0,0,0,0,0,0,0,0,0,0,0,0,0,0,0,0,0,0,0,0,0,0,0,0,0,0,0,0,0,0],"participation":1,"participationMin":94,"index":{"total":0,"off":0,"def":0}},"49012":{"stats":[0,0,0,0,0,0,0,0,0,0,0,0,0,0,0,0,0,0,0,0,0,0,0,0,0,0,0,0,0,0,0,0,0,0,0,0,0,0,0,0,0,0,0,0,0,0,0,0,0,0,0,0,0,1,0,1,2,0,0,0,0,0,0,0,0,0,0,0,0,0,0,0,0,0,0,0,0,0,0,0,0,0,0,0,0,0,0,0,0,0,0,0,0],"participation":1,"participationMin":94,"index":{"total":-75,"off":-37.5,"def":-37.5}},"104215":{"stats":[0,0,0,0,0,0,0,0,0,0,0,0,0,0,0,0,0,0,0,0,0,0,0,0,0,0,0,0,0,0,0,0,0,0,0,0,0,0,0,0,0,0,0,0,0,0,0,0,0,0,0,0,0,0,0,1,2,0,0,0,0,0,0,0,0,0,0,0,0,0,0,0,0,0,0,0,0,0,0,0,0,0,0,0,0,0,0,0,0,0,0,0,0],"participation":1,"participationMin":94,"index":{"total":0,"off":0,"def":0}},"120537":{"stats":[0,0,0,0,0,0,0,0,0,0,0,0,0,0,0,0,0,0,0,0,0,0,0,0,0,0,0,0,0,0,0,0,0,0,0,0,0,0,0,0,0,0,0,0,0,0,0,0,0,0,0,0,0,0,0,1,2,0,0,0,0,0,0,0,0,0,0,0,0,0,0,0,0,0,0,0,0,0,0,0,0,0,0,0,0,0,0,0,0,0,0,0,0],"participation":1,"participationMin":94,"index":{"total":0,"off":0,"def":0}},"168143":{"stats":[0,0,0,0,0,0,0,0,0,0,0,0,0,0,0,0,0,0,0,0,0,0,0,0,0,0,0,0,0,0,0,0,0,0,0,0,0,0,0,0,0,0,0,0,0,0,0,0,0,0,0,0,0,0,0,1,1,0,0,0,0,0,0,0,0,0,0,0,0,0,0,0,0,0,0,0,0,0,0,0,0,0,0,0,0,0,0,0,0,0,0,0,0],"participation":0.47872340425532,"participationMin":45,"index":{"total":0,"off":0,"def":0}},"92174":{"stats":[0,0,0,0,0,0,0,0,0,0,0,0,0,0,0,0,0,0,0,0,0,0,0,0,0,0,0,0,0,0,0,0,0,0,0,0,0,0,0,0,0,0,0,0,0,0,0,0,0,0,0,0,0,0,0,1,2,0,0,0,0,0,0,0,0,0,0,0,0,0,0,0,0,0,0,0,0,0,0,0,0,0,0,0,0,0,0,0,0,0,0,0,0],"participation":0.47872340425532,"participationMin":45,"index":{"total":0,"off":0,"def":0}},"110524":{"stats":[0,0,0,0,0,0,0,0,0,1,0,0,0,0,0,0,0,0,0,0,0,0,0,0,0,0,0,0,0,0,0,0,0,0,0,0,0,0,0,0,0,0,0,0,0,0,0,0,0,0,0,0,0,1,0,1,2,0,0,0,0,0,0,0,0,0,0,0,0,0,0,0,0,0,0,0,0,0,0,0,0,0,0,0,0,0,0,0,0,0,0,0,0],"participation":1,"participationMin":94,"index":{"total":252,"off":289.5,"def":-37.5}},"228316":{"stats":[0,0,0,0,0,0,0,0,0,0,0,0,0,0,0,0,0,0,0,0,0,0,0,0,0,0,0,0,0,0,0,0,0,0,0,0,0,0,0,0,0,0,0,0,0,0,0,0,0,0,0,0,0,0,0,0,0,0,0,0,0,0,0,0,0,0,0,0,0,0,0,0,0,0,0,0,0,0,0,0,0,0,0,0,0,0,0,0,0,0,0,0,0],"participation":0,"participationMin":0,"index":{"total":0,"off":0,"def":0}},"41273":{"stats":[0,0,0,0,0,0,0,0,0,0,0,0,0,0,0,0,0,0,0,0,0,0,0,0,0,0,0,0,0,0,0,0,0,0,0,0,0,0,0,0,0,0,0,0,0,0,0,0,0,0,0,0,0,0,0,0,0,0,0,0,0,0,0,0,0,0,0,0,0,0,0,0,0,0,0,0,0,0,0,0,0,0,0,0,0,0,0,0,0,0,0,0,0],"participation":0.27659574468085,"participationMin":26,"index":{"total":0,"off":0,"def":0}},"233275":{"stats":[0,0,0,0,0,0,0,0,0,0,0,0,0,0,0,0,0,0,0,0,0,0,0,0,0,0,0,0,0,0,0,0,0,0,0,0,0,0,0,0,0,0,0,0,0,0,0,0,0,0,0,0,0,0,0,0,0,0,0,0,0,0,0,0,0,0,0,0,0,0,0,0,0,0,0,0,0,0,0,0,0,0,0,0,0,0,0,0,0,0,0,0,0],"participation":0,"participationMin":0,"index":{"total":0,"off":0,"def":0}},"51932":{"stats":[0,0,0,0,0,0,0,0,0,0,0,0,0,0,0,0,0,0,0,0,0,0,0,0,0,0,0,0,0,0,0,0,0,0,0,0,0,0,0,0,0,0,0,0,0,0,0,0,0,0,0,0,0,0,0,0,0,0,0,0,0,0,0,0,0,0,0,0,0,0,0,0,0,0,0,0,0,0,0,0,0,0,0,0,0,0,0,0,0,0,0,0,0],"participation":0,"participationMin":0,"index":{"total":0,"off":0,"def":0}},"51935":{"stats":[0,0,0,0,0,0,0,0,0,0,0,0,0,0,0,0,0,0,0,0,0,0,0,0,0,0,0,0,0,0,0,0,0,0,0,0,0,0,0,0,0,0,0,0,0,0,0,0,0,0,0,0,0,0,0,0,0,0,0,0,0,0,0,0,0,0,0,0,0,0,0,0,0,0,0,0,0,0,0,0,0,0,0,0,0,0,0,0,0,0,0,0,0],"participation":0.52127659574468,"participationMin":49,"index":{"total":0,"off":0,"def":0}},"180177":{"stats":[0,0,0,0,0,0,0,0,0,0,0,0,0,0,0,0,0,0,0,0,0,0,0,0,0,0,0,0,0,0,0,0,0,0,0,0,0,0,0,0,0,0,0,0,0,0,0,0,0,0,0,0,0,0,0,0,0,0,0,0,0,0,0,0,0,0,0,0,0,0,0,0,0,0,0,0,0,0,0,0,0,0,0,0,0,0,0,0,0,0,0,0,0],"participation":0,"participationMin":0,"index":{"total":0,"off":0,"def":0}},"192788":{"stats":[0,0,0,0,0,0,0,0,0,0,0,0,0,0,0,0,0,0,0,0,0,0,0,0,0,0,0,0,0,0,0,0,0,0,0,0,0,0,0,0,0,0,0,0,0,0,0,0,0,0,0,0,0,0,0,0,1,0,0,0,0,0,0,0,0,0,0,0,0,0,0,0,0,0,0,0,0,0,0,0,0,0,0,0,0,0,0,0,0,0,0,0,0],"participation":0.52127659574468,"participationMin":49,"index":{"total":0,"off":0,"def":0}}},"score_Home":3,"score_Away":1,"running":false,"progress":5640,"sinceMatchBegin":6716,"f9Id":508831,"relevance":100,"halfscore_Home":2,"halfscore_Away":0}],"range":{"from":null,"till":null}}}